{"id":2072,"name":"iCollectionRevisionModSchema","kind":32,"kindString":"Variable","flags":{"isConst":true},"children":[],"sources":[{"fileName":"src/nexus/schemas.ts","fullFileName":"/home/runner/work/npc-vortex-api/npc-vortex-api/src/nexus/schemas.ts","line":381,"character":13,"url":"https://github.com/toebeann/npc-vortex-api/blob/b51a728/src/nexus/schemas.ts#L381"}],"type":{"type":"reference","typeArguments":[{"type":"reflection","declaration":{"id":2073,"name":"__type","kind":65536,"kindString":"Type literal","flags":{},"children":[{"id":2074,"name":"collectionRevisionId","kind":1024,"kindString":"Property","flags":{},"sources":[{"fileName":"src/nexus/schemas.ts","line":382,"character":4,"url":"https://github.com/toebeann/npc-vortex-api/blob/b51a728/src/nexus/schemas.ts#L382"}],"type":{"type":"reference","name":"ZodNumber","qualifiedName":"ZodNumber","package":"zod"},"defaultValue":"..."},{"id":2075,"name":"file","kind":1024,"kindString":"Property","flags":{},"sources":[{"fileName":"src/nexus/schemas.ts","line":383,"character":4,"url":"https://github.com/toebeann/npc-vortex-api/blob/b51a728/src/nexus/schemas.ts#L383"}],"type":{"type":"reference","typeArguments":[{"type":"reference","typeArguments":[{"type":"reflection","declaration":{"id":2076,"name":"__type","kind":65536,"kindString":"Type literal","flags":{},"children":[{"id":2077,"name":"categoryId","kind":1024,"kindString":"Property","flags":{},"sources":[{"fileName":"src/nexus/schemas.ts","line":358,"character":4,"url":"https://github.com/toebeann/npc-vortex-api/blob/b51a728/src/nexus/schemas.ts#L358"}],"type":{"type":"reference","name":"ZodNumber","qualifiedName":"ZodNumber","package":"zod"},"defaultValue":"..."},{"id":2078,"name":"count","kind":1024,"kindString":"Property","flags":{},"sources":[{"fileName":"src/nexus/schemas.ts","line":359,"character":4,"url":"https://github.com/toebeann/npc-vortex-api/blob/b51a728/src/nexus/schemas.ts#L359"}],"type":{"type":"reference","name":"ZodNumber","qualifiedName":"ZodNumber","package":"zod"},"defaultValue":"..."},{"id":2079,"name":"date","kind":1024,"kindString":"Property","flags":{},"sources":[{"fileName":"src/nexus/schemas.ts","line":360,"character":4,"url":"https://github.com/toebeann/npc-vortex-api/blob/b51a728/src/nexus/schemas.ts#L360"}],"type":{"type":"reference","name":"ZodNumber","qualifiedName":"ZodNumber","package":"zod"},"defaultValue":"..."},{"id":2080,"name":"description","kind":1024,"kindString":"Property","flags":{},"sources":[{"fileName":"src/nexus/schemas.ts","line":361,"character":4,"url":"https://github.com/toebeann/npc-vortex-api/blob/b51a728/src/nexus/schemas.ts#L361"}],"type":{"type":"reference","name":"ZodString","qualifiedName":"ZodString","package":"zod"},"defaultValue":"..."},{"id":2081,"name":"fileId","kind":1024,"kindString":"Property","flags":{},"sources":[{"fileName":"src/nexus/schemas.ts","line":362,"character":4,"url":"https://github.com/toebeann/npc-vortex-api/blob/b51a728/src/nexus/schemas.ts#L362"}],"type":{"type":"reference","name":"ZodNumber","qualifiedName":"ZodNumber","package":"zod"},"defaultValue":"..."},{"id":2082,"name":"game","kind":1024,"kindString":"Property","flags":{},"sources":[{"fileName":"src/nexus/schemas.ts","line":363,"character":4,"url":"https://github.com/toebeann/npc-vortex-api/blob/b51a728/src/nexus/schemas.ts#L363"}],"type":{"type":"reference","typeArguments":[{"type":"reflection","declaration":{"id":2083,"name":"__type","kind":65536,"kindString":"Type literal","flags":{},"children":[{"id":2085,"name":"domainName","kind":1024,"kindString":"Property","flags":{},"sources":[{"fileName":"src/nexus/schemas.ts","line":252,"character":4,"url":"https://github.com/toebeann/npc-vortex-api/blob/b51a728/src/nexus/schemas.ts#L252"}],"type":{"type":"reference","name":"ZodString","qualifiedName":"ZodString","package":"zod"},"defaultValue":"..."},{"id":2084,"name":"id","kind":1024,"kindString":"Property","flags":{},"sources":[{"fileName":"src/nexus/schemas.ts","line":251,"character":4,"url":"https://github.com/toebeann/npc-vortex-api/blob/b51a728/src/nexus/schemas.ts#L251"}],"type":{"type":"reference","typeArguments":[{"type":"reference","name":"ZodNumber","qualifiedName":"ZodNumber","package":"zod"}],"name":"ZodOptional","qualifiedName":"ZodOptional","package":"zod"},"defaultValue":"..."},{"id":2086,"name":"name","kind":1024,"kindString":"Property","flags":{},"sources":[{"fileName":"src/nexus/schemas.ts","line":253,"character":4,"url":"https://github.com/toebeann/npc-vortex-api/blob/b51a728/src/nexus/schemas.ts#L253"}],"type":{"type":"reference","typeArguments":[{"type":"reference","name":"ZodString","qualifiedName":"ZodString","package":"zod"}],"name":"ZodOptional","qualifiedName":"ZodOptional","package":"zod"},"defaultValue":"..."}],"groups":[{"title":"Properties","children":[2085,2084,2086]}],"sources":[{"fileName":"src/nexus/schemas.ts","line":250,"character":36,"url":"https://github.com/toebeann/npc-vortex-api/blob/b51a728/src/nexus/schemas.ts#L250"}]}},{"type":"literal","value":"strip"},{"type":"reference","name":"ZodTypeAny","qualifiedName":"ZodTypeAny","package":"zod"},{"type":"reflection","declaration":{"id":2087,"name":"__type","kind":65536,"kindString":"Type literal","flags":{},"children":[{"id":2090,"name":"domainName","kind":1024,"kindString":"Property","flags":{},"sources":[{"fileName":"src/nexus/schemas.ts","line":252,"character":4,"url":"https://github.com/toebeann/npc-vortex-api/blob/b51a728/src/nexus/schemas.ts#L252"}],"type":{"type":"intrinsic","name":"string"},"defaultValue":"..."},{"id":2088,"name":"id","kind":1024,"kindString":"Property","flags":{},"sources":[{"fileName":"src/nexus/schemas.ts","line":251,"character":4,"url":"https://github.com/toebeann/npc-vortex-api/blob/b51a728/src/nexus/schemas.ts#L251"}],"type":{"type":"union","types":[{"type":"intrinsic","name":"undefined"},{"type":"intrinsic","name":"number"}]},"defaultValue":"..."},{"id":2089,"name":"name","kind":1024,"kindString":"Property","flags":{},"sources":[{"fileName":"src/nexus/schemas.ts","line":253,"character":4,"url":"https://github.com/toebeann/npc-vortex-api/blob/b51a728/src/nexus/schemas.ts#L253"}],"type":{"type":"union","types":[{"type":"intrinsic","name":"undefined"},{"type":"intrinsic","name":"string"}]},"defaultValue":"..."}],"groups":[{"title":"Properties","children":[2090,2088,2089]}],"sources":[{"fileName":"node_modules/.pnpm/zod@3.21.0/node_modules/zod/lib/types.d.ts","line":977,"character":123}]}},{"type":"reflection","declaration":{"id":2091,"name":"__type","kind":65536,"kindString":"Type literal","flags":{},"children":[{"id":2094,"name":"domainName","kind":1024,"kindString":"Property","flags":{},"sources":[{"fileName":"src/nexus/schemas.ts","line":252,"character":4,"url":"https://github.com/toebeann/npc-vortex-api/blob/b51a728/src/nexus/schemas.ts#L252"}],"type":{"type":"intrinsic","name":"string"},"defaultValue":"..."},{"id":2092,"name":"id","kind":1024,"kindString":"Property","flags":{},"sources":[{"fileName":"src/nexus/schemas.ts","line":251,"character":4,"url":"https://github.com/toebeann/npc-vortex-api/blob/b51a728/src/nexus/schemas.ts#L251"}],"type":{"type":"union","types":[{"type":"intrinsic","name":"undefined"},{"type":"intrinsic","name":"number"}]},"defaultValue":"..."},{"id":2093,"name":"name","kind":1024,"kindString":"Property","flags":{},"sources":[{"fileName":"src/nexus/schemas.ts","line":253,"character":4,"url":"https://github.com/toebeann/npc-vortex-api/blob/b51a728/src/nexus/schemas.ts#L253"}],"type":{"type":"union","types":[{"type":"intrinsic","name":"undefined"},{"type":"intrinsic","name":"string"}]},"defaultValue":"..."}],"groups":[{"title":"Properties","children":[2094,2092,2093]}],"sources":[{"fileName":"node_modules/.pnpm/zod@3.21.0/node_modules/zod/lib/types.d.ts","line":977,"character":194}]}}],"name":"ZodObject","qualifiedName":"ZodObject","package":"zod"},"defaultValue":"iGameSchema"},{"id":2095,"name":"manager","kind":1024,"kindString":"Property","flags":{},"sources":[{"fileName":"src/nexus/schemas.ts","line":364,"character":4,"url":"https://github.com/toebeann/npc-vortex-api/blob/b51a728/src/nexus/schemas.ts#L364"}],"type":{"type":"reference","name":"ZodNumber","qualifiedName":"ZodNumber","package":"zod"},"defaultValue":"..."},{"id":2096,"name":"mod","kind":1024,"kindString":"Property","flags":{},"sources":[{"fileName":"src/nexus/schemas.ts","line":365,"character":4,"url":"https://github.com/toebeann/npc-vortex-api/blob/b51a728/src/nexus/schemas.ts#L365"}],"type":{"type":"reference","typeArguments":[{"type":"reflection","declaration":{"id":2097,"name":"__type","kind":65536,"kindString":"Type literal","flags":{},"children":[{"id":2098,"name":"author","kind":1024,"kindString":"Property","flags":{},"sources":[{"fileName":"src/nexus/schemas.ts","line":338,"character":4,"url":"https://github.com/toebeann/npc-vortex-api/blob/b51a728/src/nexus/schemas.ts#L338"}],"type":{"type":"reference","typeArguments":[{"type":"reference","name":"ZodString","qualifiedName":"ZodString","package":"zod"}],"name":"ZodOptional","qualifiedName":"ZodOptional","package":"zod"},"defaultValue":"..."},{"id":2099,"name":"category","kind":1024,"kindString":"Property","flags":{},"sources":[{"fileName":"src/nexus/schemas.ts","line":339,"character":4,"url":"https://github.com/toebeann/npc-vortex-api/blob/b51a728/src/nexus/schemas.ts#L339"}],"type":{"type":"reference","name":"ZodString","qualifiedName":"ZodString","package":"zod"},"defaultValue":"..."},{"id":2100,"name":"description","kind":1024,"kindString":"Property","flags":{},"sources":[{"fileName":"src/nexus/schemas.ts","line":340,"character":4,"url":"https://github.com/toebeann/npc-vortex-api/blob/b51a728/src/nexus/schemas.ts#L340"}],"type":{"type":"reference","name":"ZodString","qualifiedName":"ZodString","package":"zod"},"defaultValue":"..."},{"id":2101,"name":"game","kind":1024,"kindString":"Property","flags":{},"sources":[{"fileName":"src/nexus/schemas.ts","line":341,"character":4,"url":"https://github.com/toebeann/npc-vortex-api/blob/b51a728/src/nexus/schemas.ts#L341"}],"type":{"type":"reference","typeArguments":[{"type":"reflection","declaration":{"id":2102,"name":"__type","kind":65536,"kindString":"Type literal","flags":{},"children":[{"id":2104,"name":"domainName","kind":1024,"kindString":"Property","flags":{},"sources":[{"fileName":"src/nexus/schemas.ts","line":252,"character":4,"url":"https://github.com/toebeann/npc-vortex-api/blob/b51a728/src/nexus/schemas.ts#L252"}],"type":{"type":"reference","name":"ZodString","qualifiedName":"ZodString","package":"zod"},"defaultValue":"..."},{"id":2103,"name":"id","kind":1024,"kindString":"Property","flags":{},"sources":[{"fileName":"src/nexus/schemas.ts","line":251,"character":4,"url":"https://github.com/toebeann/npc-vortex-api/blob/b51a728/src/nexus/schemas.ts#L251"}],"type":{"type":"reference","typeArguments":[{"type":"reference","name":"ZodNumber","qualifiedName":"ZodNumber","package":"zod"}],"name":"ZodOptional","qualifiedName":"ZodOptional","package":"zod"},"defaultValue":"..."},{"id":2105,"name":"name","kind":1024,"kindString":"Property","flags":{},"sources":[{"fileName":"src/nexus/schemas.ts","line":253,"character":4,"url":"https://github.com/toebeann/npc-vortex-api/blob/b51a728/src/nexus/schemas.ts#L253"}],"type":{"type":"reference","typeArguments":[{"type":"reference","name":"ZodString","qualifiedName":"ZodString","package":"zod"}],"name":"ZodOptional","qualifiedName":"ZodOptional","package":"zod"},"defaultValue":"..."}],"groups":[{"title":"Properties","children":[2104,2103,2105]}],"sources":[{"fileName":"src/nexus/schemas.ts","line":250,"character":36,"url":"https://github.com/toebeann/npc-vortex-api/blob/b51a728/src/nexus/schemas.ts#L250"}]}},{"type":"literal","value":"strip"},{"type":"reference","name":"ZodTypeAny","qualifiedName":"ZodTypeAny","package":"zod"},{"type":"reflection","declaration":{"id":2106,"name":"__type","kind":65536,"kindString":"Type literal","flags":{},"children":[{"id":2109,"name":"domainName","kind":1024,"kindString":"Property","flags":{},"sources":[{"fileName":"src/nexus/schemas.ts","line":252,"character":4,"url":"https://github.com/toebeann/npc-vortex-api/blob/b51a728/src/nexus/schemas.ts#L252"}],"type":{"type":"intrinsic","name":"string"},"defaultValue":"..."},{"id":2107,"name":"id","kind":1024,"kindString":"Property","flags":{},"sources":[{"fileName":"src/nexus/schemas.ts","line":251,"character":4,"url":"https://github.com/toebeann/npc-vortex-api/blob/b51a728/src/nexus/schemas.ts#L251"}],"type":{"type":"union","types":[{"type":"intrinsic","name":"undefined"},{"type":"intrinsic","name":"number"}]},"defaultValue":"..."},{"id":2108,"name":"name","kind":1024,"kindString":"Property","flags":{},"sources":[{"fileName":"src/nexus/schemas.ts","line":253,"character":4,"url":"https://github.com/toebeann/npc-vortex-api/blob/b51a728/src/nexus/schemas.ts#L253"}],"type":{"type":"union","types":[{"type":"intrinsic","name":"undefined"},{"type":"intrinsic","name":"string"}]},"defaultValue":"..."}],"groups":[{"title":"Properties","children":[2109,2107,2108]}],"sources":[{"fileName":"node_modules/.pnpm/zod@3.21.0/node_modules/zod/lib/types.d.ts","line":977,"character":123}]}},{"type":"reflection","declaration":{"id":2110,"name":"__type","kind":65536,"kindString":"Type literal","flags":{},"children":[{"id":2113,"name":"domainName","kind":1024,"kindString":"Property","flags":{},"sources":[{"fileName":"src/nexus/schemas.ts","line":252,"character":4,"url":"https://github.com/toebeann/npc-vortex-api/blob/b51a728/src/nexus/schemas.ts#L252"}],"type":{"type":"intrinsic","name":"string"},"defaultValue":"..."},{"id":2111,"name":"id","kind":1024,"kindString":"Property","flags":{},"sources":[{"fileName":"src/nexus/schemas.ts","line":251,"character":4,"url":"https://github.com/toebeann/npc-vortex-api/blob/b51a728/src/nexus/schemas.ts#L251"}],"type":{"type":"union","types":[{"type":"intrinsic","name":"undefined"},{"type":"intrinsic","name":"number"}]},"defaultValue":"..."},{"id":2112,"name":"name","kind":1024,"kindString":"Property","flags":{},"sources":[{"fileName":"src/nexus/schemas.ts","line":253,"character":4,"url":"https://github.com/toebeann/npc-vortex-api/blob/b51a728/src/nexus/schemas.ts#L253"}],"type":{"type":"union","types":[{"type":"intrinsic","name":"undefined"},{"type":"intrinsic","name":"string"}]},"defaultValue":"..."}],"groups":[{"title":"Properties","children":[2113,2111,2112]}],"sources":[{"fileName":"node_modules/.pnpm/zod@3.21.0/node_modules/zod/lib/types.d.ts","line":977,"character":194}]}}],"name":"ZodObject","qualifiedName":"ZodObject","package":"zod"},"defaultValue":"iGameSchema"},{"id":2114,"name":"gameId","kind":1024,"kindString":"Property","flags":{},"sources":[{"fileName":"src/nexus/schemas.ts","line":342,"character":4,"url":"https://github.com/toebeann/npc-vortex-api/blob/b51a728/src/nexus/schemas.ts#L342"}],"type":{"type":"reference","name":"ZodNumber","qualifiedName":"ZodNumber","package":"zod"},"defaultValue":"..."},{"id":2115,"name":"id","kind":1024,"kindString":"Property","flags":{},"sources":[{"fileName":"src/nexus/schemas.ts","line":343,"character":4,"url":"https://github.com/toebeann/npc-vortex-api/blob/b51a728/src/nexus/schemas.ts#L343"}],"type":{"type":"reference","name":"ZodNumber","qualifiedName":"ZodNumber","package":"zod"},"defaultValue":"..."},{"id":2116,"name":"ipAddress","kind":1024,"kindString":"Property","flags":{},"sources":[{"fileName":"src/nexus/schemas.ts","line":344,"character":4,"url":"https://github.com/toebeann/npc-vortex-api/blob/b51a728/src/nexus/schemas.ts#L344"}],"type":{"type":"reference","name":"ZodString","qualifiedName":"ZodString","package":"zod"},"defaultValue":"..."},{"id":2117,"name":"modCategory","kind":1024,"kindString":"Property","flags":{},"sources":[{"fileName":"src/nexus/schemas.ts","line":345,"character":4,"url":"https://github.com/toebeann/npc-vortex-api/blob/b51a728/src/nexus/schemas.ts#L345"}],"type":{"type":"reference","typeArguments":[{"type":"reflection","declaration":{"id":2118,"name":"__type","kind":65536,"kindString":"Type literal","flags":{},"children":[{"id":2119,"name":"category_id","kind":1024,"kindString":"Property","flags":{},"sources":[{"fileName":"src/nexus/schemas.ts","line":328,"character":4,"url":"https://github.com/toebeann/npc-vortex-api/blob/b51a728/src/nexus/schemas.ts#L328"}],"type":{"type":"reference","name":"ZodNumber","qualifiedName":"ZodNumber","package":"zod"},"defaultValue":"..."},{"id":2120,"name":"name","kind":1024,"kindString":"Property","flags":{},"sources":[{"fileName":"src/nexus/schemas.ts","line":329,"character":4,"url":"https://github.com/toebeann/npc-vortex-api/blob/b51a728/src/nexus/schemas.ts#L329"}],"type":{"type":"reference","name":"ZodString","qualifiedName":"ZodString","package":"zod"},"defaultValue":"..."},{"id":2121,"name":"parent_category","kind":1024,"kindString":"Property","flags":{},"sources":[{"fileName":"src/nexus/schemas.ts","line":330,"character":4,"url":"https://github.com/toebeann/npc-vortex-api/blob/b51a728/src/nexus/schemas.ts#L330"}],"type":{"type":"reference","typeArguments":[{"type":"tuple","elements":[{"type":"reference","name":"ZodNumber","qualifiedName":"ZodNumber","package":"zod"},{"type":"reference","typeArguments":[{"type":"literal","value":false}],"name":"ZodLiteral","qualifiedName":"ZodLiteral","package":"zod"}]}],"name":"ZodUnion","qualifiedName":"ZodUnion","package":"zod"},"defaultValue":"..."}],"groups":[{"title":"Properties","children":[2119,2120,2121]}],"sources":[{"fileName":"src/nexus/schemas.ts","line":327,"character":43,"url":"https://github.com/toebeann/npc-vortex-api/blob/b51a728/src/nexus/schemas.ts#L327"}]}},{"type":"literal","value":"strip"},{"type":"reference","name":"ZodTypeAny","qualifiedName":"ZodTypeAny","package":"zod"},{"type":"reflection","declaration":{"id":2122,"name":"__type","kind":65536,"kindString":"Type literal","flags":{},"children":[{"id":2124,"name":"category_id","kind":1024,"kindString":"Property","flags":{},"sources":[{"fileName":"src/nexus/schemas.ts","line":328,"character":4,"url":"https://github.com/toebeann/npc-vortex-api/blob/b51a728/src/nexus/schemas.ts#L328"}],"type":{"type":"intrinsic","name":"number"},"defaultValue":"..."},{"id":2123,"name":"name","kind":1024,"kindString":"Property","flags":{},"sources":[{"fileName":"src/nexus/schemas.ts","line":329,"character":4,"url":"https://github.com/toebeann/npc-vortex-api/blob/b51a728/src/nexus/schemas.ts#L329"}],"type":{"type":"intrinsic","name":"string"},"defaultValue":"..."},{"id":2125,"name":"parent_category","kind":1024,"kindString":"Property","flags":{},"sources":[{"fileName":"src/nexus/schemas.ts","line":330,"character":4,"url":"https://github.com/toebeann/npc-vortex-api/blob/b51a728/src/nexus/schemas.ts#L330"}],"type":{"type":"union","types":[{"type":"intrinsic","name":"number"},{"type":"literal","value":false}]},"defaultValue":"..."}],"groups":[{"title":"Properties","children":[2124,2123,2125]}],"sources":[{"fileName":"node_modules/.pnpm/zod@3.21.0/node_modules/zod/lib/types.d.ts","line":977,"character":123}]}},{"type":"reflection","declaration":{"id":2126,"name":"__type","kind":65536,"kindString":"Type literal","flags":{},"children":[{"id":2128,"name":"category_id","kind":1024,"kindString":"Property","flags":{},"sources":[{"fileName":"src/nexus/schemas.ts","line":328,"character":4,"url":"https://github.com/toebeann/npc-vortex-api/blob/b51a728/src/nexus/schemas.ts#L328"}],"type":{"type":"intrinsic","name":"number"},"defaultValue":"..."},{"id":2127,"name":"name","kind":1024,"kindString":"Property","flags":{},"sources":[{"fileName":"src/nexus/schemas.ts","line":329,"character":4,"url":"https://github.com/toebeann/npc-vortex-api/blob/b51a728/src/nexus/schemas.ts#L329"}],"type":{"type":"intrinsic","name":"string"},"defaultValue":"..."},{"id":2129,"name":"parent_category","kind":1024,"kindString":"Property","flags":{},"sources":[{"fileName":"src/nexus/schemas.ts","line":330,"character":4,"url":"https://github.com/toebeann/npc-vortex-api/blob/b51a728/src/nexus/schemas.ts#L330"}],"type":{"type":"union","types":[{"type":"intrinsic","name":"number"},{"type":"literal","value":false}]},"defaultValue":"..."}],"groups":[{"title":"Properties","children":[2128,2127,2129]}],"sources":[{"fileName":"node_modules/.pnpm/zod@3.21.0/node_modules/zod/lib/types.d.ts","line":977,"character":194}]}}],"name":"ZodObject","qualifiedName":"ZodObject","package":"zod"},"defaultValue":"iModCategorySchema"},{"id":2130,"name":"modId","kind":1024,"kindString":"Property","flags":{},"sources":[{"fileName":"src/nexus/schemas.ts","line":346,"character":4,"url":"https://github.com/toebeann/npc-vortex-api/blob/b51a728/src/nexus/schemas.ts#L346"}],"type":{"type":"reference","name":"ZodNumber","qualifiedName":"ZodNumber","package":"zod"},"defaultValue":"..."},{"id":2131,"name":"name","kind":1024,"kindString":"Property","flags":{},"sources":[{"fileName":"src/nexus/schemas.ts","line":347,"character":4,"url":"https://github.com/toebeann/npc-vortex-api/blob/b51a728/src/nexus/schemas.ts#L347"}],"type":{"type":"reference","name":"ZodString","qualifiedName":"ZodString","package":"zod"},"defaultValue":"..."},{"id":2132,"name":"pictureUrl","kind":1024,"kindString":"Property","flags":{},"sources":[{"fileName":"src/nexus/schemas.ts","line":348,"character":4,"url":"https://github.com/toebeann/npc-vortex-api/blob/b51a728/src/nexus/schemas.ts#L348"}],"type":{"type":"reference","typeArguments":[{"type":"reference","name":"ZodString","qualifiedName":"ZodString","package":"zod"}],"name":"ZodOptional","qualifiedName":"ZodOptional","package":"zod"},"defaultValue":"..."},{"id":2133,"name":"status","kind":1024,"kindString":"Property","flags":{},"sources":[{"fileName":"src/nexus/schemas.ts","line":349,"character":4,"url":"https://github.com/toebeann/npc-vortex-api/blob/b51a728/src/nexus/schemas.ts#L349"}],"type":{"type":"reference","name":"ZodString","qualifiedName":"ZodString","package":"zod"},"defaultValue":"..."},{"id":2134,"name":"summary","kind":1024,"kindString":"Property","flags":{},"sources":[{"fileName":"src/nexus/schemas.ts","line":350,"character":4,"url":"https://github.com/toebeann/npc-vortex-api/blob/b51a728/src/nexus/schemas.ts#L350"}],"type":{"type":"reference","name":"ZodString","qualifiedName":"ZodString","package":"zod"},"defaultValue":"..."},{"id":2135,"name":"trackingData","kind":1024,"kindString":"Property","flags":{},"sources":[{"fileName":"src/nexus/schemas.ts","line":351,"character":4,"url":"https://github.com/toebeann/npc-vortex-api/blob/b51a728/src/nexus/schemas.ts#L351"}],"type":{"type":"reference","typeArguments":[{"type":"reflection","declaration":{"id":2136,"name":"__type","kind":65536,"kindString":"Type literal","flags":{},"children":[{"id":2137,"name":"test","kind":1024,"kindString":"Property","flags":{},"sources":[{"fileName":"src/nexus/schemas.ts","line":334,"character":4,"url":"https://github.com/toebeann/npc-vortex-api/blob/b51a728/src/nexus/schemas.ts#L334"}],"type":{"type":"reference","typeArguments":[{"type":"reference","name":"ZodNumber","qualifiedName":"ZodNumber","package":"zod"}],"name":"ZodOptional","qualifiedName":"ZodOptional","package":"zod"},"defaultValue":"..."}],"groups":[{"title":"Properties","children":[2137]}],"sources":[{"fileName":"src/nexus/schemas.ts","line":333,"character":45,"url":"https://github.com/toebeann/npc-vortex-api/blob/b51a728/src/nexus/schemas.ts#L333"}]}},{"type":"literal","value":"strip"},{"type":"reference","name":"ZodTypeAny","qualifiedName":"ZodTypeAny","package":"zod"},{"type":"reflection","declaration":{"id":2138,"name":"__type","kind":65536,"kindString":"Type literal","flags":{},"children":[{"id":2139,"name":"test","kind":1024,"kindString":"Property","flags":{},"sources":[{"fileName":"src/nexus/schemas.ts","line":334,"character":4,"url":"https://github.com/toebeann/npc-vortex-api/blob/b51a728/src/nexus/schemas.ts#L334"}],"type":{"type":"union","types":[{"type":"intrinsic","name":"undefined"},{"type":"intrinsic","name":"number"}]},"defaultValue":"..."}],"groups":[{"title":"Properties","children":[2139]}],"sources":[{"fileName":"node_modules/.pnpm/zod@3.21.0/node_modules/zod/lib/types.d.ts","line":977,"character":123}]}},{"type":"reflection","declaration":{"id":2140,"name":"__type","kind":65536,"kindString":"Type literal","flags":{},"children":[{"id":2141,"name":"test","kind":1024,"kindString":"Property","flags":{},"sources":[{"fileName":"src/nexus/schemas.ts","line":334,"character":4,"url":"https://github.com/toebeann/npc-vortex-api/blob/b51a728/src/nexus/schemas.ts#L334"}],"type":{"type":"union","types":[{"type":"intrinsic","name":"undefined"},{"type":"intrinsic","name":"number"}]},"defaultValue":"..."}],"groups":[{"title":"Properties","children":[2141]}],"sources":[{"fileName":"node_modules/.pnpm/zod@3.21.0/node_modules/zod/lib/types.d.ts","line":977,"character":194}]}}],"name":"ZodObject","qualifiedName":"ZodObject","package":"zod"},"defaultValue":"iTrackingStateSchema"},{"id":2142,"name":"uid","kind":1024,"kindString":"Property","flags":{},"sources":[{"fileName":"src/nexus/schemas.ts","line":352,"character":4,"url":"https://github.com/toebeann/npc-vortex-api/blob/b51a728/src/nexus/schemas.ts#L352"}],"type":{"type":"reference","name":"ZodString","qualifiedName":"ZodString","package":"zod"},"defaultValue":"..."},{"id":2143,"name":"uploader","kind":1024,"kindString":"Property","flags":{},"sources":[{"fileName":"src/nexus/schemas.ts","line":353,"character":4,"url":"https://github.com/toebeann/npc-vortex-api/blob/b51a728/src/nexus/schemas.ts#L353"}],"type":{"type":"reference","typeArguments":[{"type":"reflection","declaration":{"id":2144,"name":"__type","kind":65536,"kindString":"Type literal","flags":{},"children":[{"id":2145,"name":"avatar","kind":1024,"kindString":"Property","flags":{},"sources":[{"fileName":"src/nexus/schemas.ts","line":271,"character":4,"url":"https://github.com/toebeann/npc-vortex-api/blob/b51a728/src/nexus/schemas.ts#L271"}],"type":{"type":"reference","name":"ZodString","qualifiedName":"ZodString","package":"zod"},"defaultValue":"..."},{"id":2146,"name":"memberId","kind":1024,"kindString":"Property","flags":{},"sources":[{"fileName":"src/nexus/schemas.ts","line":272,"character":4,"url":"https://github.com/toebeann/npc-vortex-api/blob/b51a728/src/nexus/schemas.ts#L272"}],"type":{"type":"reference","name":"ZodNumber","qualifiedName":"ZodNumber","package":"zod"},"defaultValue":"..."},{"id":2147,"name":"name","kind":1024,"kindString":"Property","flags":{},"sources":[{"fileName":"src/nexus/schemas.ts","line":273,"character":4,"url":"https://github.com/toebeann/npc-vortex-api/blob/b51a728/src/nexus/schemas.ts#L273"}],"type":{"type":"reference","name":"ZodString","qualifiedName":"ZodString","package":"zod"},"defaultValue":"..."}],"groups":[{"title":"Properties","children":[2145,2146,2147]}],"sources":[{"fileName":"src/nexus/schemas.ts","line":270,"character":41,"url":"https://github.com/toebeann/npc-vortex-api/blob/b51a728/src/nexus/schemas.ts#L270"}]}},{"type":"literal","value":"strip"},{"type":"reference","name":"ZodTypeAny","qualifiedName":"ZodTypeAny","package":"zod"},{"type":"reflection","declaration":{"id":2148,"name":"__type","kind":65536,"kindString":"Type literal","flags":{},"children":[{"id":2150,"name":"avatar","kind":1024,"kindString":"Property","flags":{},"sources":[{"fileName":"src/nexus/schemas.ts","line":271,"character":4,"url":"https://github.com/toebeann/npc-vortex-api/blob/b51a728/src/nexus/schemas.ts#L271"}],"type":{"type":"intrinsic","name":"string"},"defaultValue":"..."},{"id":2151,"name":"memberId","kind":1024,"kindString":"Property","flags":{},"sources":[{"fileName":"src/nexus/schemas.ts","line":272,"character":4,"url":"https://github.com/toebeann/npc-vortex-api/blob/b51a728/src/nexus/schemas.ts#L272"}],"type":{"type":"intrinsic","name":"number"},"defaultValue":"..."},{"id":2149,"name":"name","kind":1024,"kindString":"Property","flags":{},"sources":[{"fileName":"src/nexus/schemas.ts","line":273,"character":4,"url":"https://github.com/toebeann/npc-vortex-api/blob/b51a728/src/nexus/schemas.ts#L273"}],"type":{"type":"intrinsic","name":"string"},"defaultValue":"..."}],"groups":[{"title":"Properties","children":[2150,2151,2149]}],"sources":[{"fileName":"node_modules/.pnpm/zod@3.21.0/node_modules/zod/lib/types.d.ts","line":977,"character":123}]}},{"type":"reflection","declaration":{"id":2152,"name":"__type","kind":65536,"kindString":"Type literal","flags":{},"children":[{"id":2154,"name":"avatar","kind":1024,"kindString":"Property","flags":{},"sources":[{"fileName":"src/nexus/schemas.ts","line":271,"character":4,"url":"https://github.com/toebeann/npc-vortex-api/blob/b51a728/src/nexus/schemas.ts#L271"}],"type":{"type":"intrinsic","name":"string"},"defaultValue":"..."},{"id":2155,"name":"memberId","kind":1024,"kindString":"Property","flags":{},"sources":[{"fileName":"src/nexus/schemas.ts","line":272,"character":4,"url":"https://github.com/toebeann/npc-vortex-api/blob/b51a728/src/nexus/schemas.ts#L272"}],"type":{"type":"intrinsic","name":"number"},"defaultValue":"..."},{"id":2153,"name":"name","kind":1024,"kindString":"Property","flags":{},"sources":[{"fileName":"src/nexus/schemas.ts","line":273,"character":4,"url":"https://github.com/toebeann/npc-vortex-api/blob/b51a728/src/nexus/schemas.ts#L273"}],"type":{"type":"intrinsic","name":"string"},"defaultValue":"..."}],"groups":[{"title":"Properties","children":[2154,2155,2153]}],"sources":[{"fileName":"node_modules/.pnpm/zod@3.21.0/node_modules/zod/lib/types.d.ts","line":977,"character":194}]}}],"name":"ZodObject","qualifiedName":"ZodObject","package":"zod"},"defaultValue":"iGraphUserSchema"},{"id":2156,"name":"version","kind":1024,"kindString":"Property","flags":{},"sources":[{"fileName":"src/nexus/schemas.ts","line":354,"character":4,"url":"https://github.com/toebeann/npc-vortex-api/blob/b51a728/src/nexus/schemas.ts#L354"}],"type":{"type":"reference","name":"ZodString","qualifiedName":"ZodString","package":"zod"},"defaultValue":"..."}],"groups":[{"title":"Properties","children":[2098,2099,2100,2101,2114,2115,2116,2117,2130,2131,2132,2133,2134,2135,2142,2143,2156]}],"sources":[{"fileName":"src/nexus/schemas.ts","line":337,"character":35,"url":"https://github.com/toebeann/npc-vortex-api/blob/b51a728/src/nexus/schemas.ts#L337"}]}},{"type":"literal","value":"strip"},{"type":"reference","name":"ZodTypeAny","qualifiedName":"ZodTypeAny","package":"zod"},{"type":"reflection","declaration":{"id":2157,"name":"__type","kind":65536,"kindString":"Type literal","flags":{},"children":[{"id":2158,"name":"author","kind":1024,"kindString":"Property","flags":{},"sources":[{"fileName":"src/nexus/schemas.ts","line":338,"character":4,"url":"https://github.com/toebeann/npc-vortex-api/blob/b51a728/src/nexus/schemas.ts#L338"}],"type":{"type":"union","types":[{"type":"intrinsic","name":"undefined"},{"type":"intrinsic","name":"string"}]},"defaultValue":"..."},{"id":2168,"name":"category","kind":1024,"kindString":"Property","flags":{},"sources":[{"fileName":"src/nexus/schemas.ts","line":339,"character":4,"url":"https://github.com/toebeann/npc-vortex-api/blob/b51a728/src/nexus/schemas.ts#L339"}],"type":{"type":"intrinsic","name":"string"},"defaultValue":"..."},{"id":2167,"name":"description","kind":1024,"kindString":"Property","flags":{},"sources":[{"fileName":"src/nexus/schemas.ts","line":340,"character":4,"url":"https://github.com/toebeann/npc-vortex-api/blob/b51a728/src/nexus/schemas.ts#L340"}],"type":{"type":"intrinsic","name":"string"},"defaultValue":"..."},{"id":2169,"name":"game","kind":1024,"kindString":"Property","flags":{},"sources":[{"fileName":"src/nexus/schemas.ts","line":341,"character":4,"url":"https://github.com/toebeann/npc-vortex-api/blob/b51a728/src/nexus/schemas.ts#L341"}],"type":{"type":"unknown","name":"{ id?: number | undefined; name?: string | undefined; domainName: string; }"},"defaultValue":"iGameSchema"},{"id":2161,"name":"gameId","kind":1024,"kindString":"Property","flags":{},"sources":[{"fileName":"src/nexus/schemas.ts","line":342,"character":4,"url":"https://github.com/toebeann/npc-vortex-api/blob/b51a728/src/nexus/schemas.ts#L342"}],"type":{"type":"intrinsic","name":"number"},"defaultValue":"..."},{"id":2163,"name":"id","kind":1024,"kindString":"Property","flags":{},"sources":[{"fileName":"src/nexus/schemas.ts","line":343,"character":4,"url":"https://github.com/toebeann/npc-vortex-api/blob/b51a728/src/nexus/schemas.ts#L343"}],"type":{"type":"intrinsic","name":"number"},"defaultValue":"..."},{"id":2170,"name":"ipAddress","kind":1024,"kindString":"Property","flags":{},"sources":[{"fileName":"src/nexus/schemas.ts","line":344,"character":4,"url":"https://github.com/toebeann/npc-vortex-api/blob/b51a728/src/nexus/schemas.ts#L344"}],"type":{"type":"intrinsic","name":"string"},"defaultValue":"..."},{"id":2171,"name":"modCategory","kind":1024,"kindString":"Property","flags":{},"sources":[{"fileName":"src/nexus/schemas.ts","line":345,"character":4,"url":"https://github.com/toebeann/npc-vortex-api/blob/b51a728/src/nexus/schemas.ts#L345"}],"type":{"type":"unknown","name":"{ name: string; category_id: number; parent_category: number | false; }"},"defaultValue":"iModCategorySchema"},{"id":2162,"name":"modId","kind":1024,"kindString":"Property","flags":{},"sources":[{"fileName":"src/nexus/schemas.ts","line":346,"character":4,"url":"https://github.com/toebeann/npc-vortex-api/blob/b51a728/src/nexus/schemas.ts#L346"}],"type":{"type":"intrinsic","name":"number"},"defaultValue":"..."},{"id":2164,"name":"name","kind":1024,"kindString":"Property","flags":{},"sources":[{"fileName":"src/nexus/schemas.ts","line":347,"character":4,"url":"https://github.com/toebeann/npc-vortex-api/blob/b51a728/src/nexus/schemas.ts#L347"}],"type":{"type":"intrinsic","name":"string"},"defaultValue":"..."},{"id":2159,"name":"pictureUrl","kind":1024,"kindString":"Property","flags":{},"sources":[{"fileName":"src/nexus/schemas.ts","line":348,"character":4,"url":"https://github.com/toebeann/npc-vortex-api/blob/b51a728/src/nexus/schemas.ts#L348"}],"type":{"type":"union","types":[{"type":"intrinsic","name":"undefined"},{"type":"intrinsic","name":"string"}]},"defaultValue":"..."},{"id":2160,"name":"status","kind":1024,"kindString":"Property","flags":{},"sources":[{"fileName":"src/nexus/schemas.ts","line":349,"character":4,"url":"https://github.com/toebeann/npc-vortex-api/blob/b51a728/src/nexus/schemas.ts#L349"}],"type":{"type":"intrinsic","name":"string"},"defaultValue":"..."},{"id":2166,"name":"summary","kind":1024,"kindString":"Property","flags":{},"sources":[{"fileName":"src/nexus/schemas.ts","line":350,"character":4,"url":"https://github.com/toebeann/npc-vortex-api/blob/b51a728/src/nexus/schemas.ts#L350"}],"type":{"type":"intrinsic","name":"string"},"defaultValue":"..."},{"id":2172,"name":"trackingData","kind":1024,"kindString":"Property","flags":{},"sources":[{"fileName":"src/nexus/schemas.ts","line":351,"character":4,"url":"https://github.com/toebeann/npc-vortex-api/blob/b51a728/src/nexus/schemas.ts#L351"}],"type":{"type":"unknown","name":"{ test?: number | undefined; }"},"defaultValue":"iTrackingStateSchema"},{"id":2173,"name":"uid","kind":1024,"kindString":"Property","flags":{},"sources":[{"fileName":"src/nexus/schemas.ts","line":352,"character":4,"url":"https://github.com/toebeann/npc-vortex-api/blob/b51a728/src/nexus/schemas.ts#L352"}],"type":{"type":"intrinsic","name":"string"},"defaultValue":"..."},{"id":2174,"name":"uploader","kind":1024,"kindString":"Property","flags":{},"sources":[{"fileName":"src/nexus/schemas.ts","line":353,"character":4,"url":"https://github.com/toebeann/npc-vortex-api/blob/b51a728/src/nexus/schemas.ts#L353"}],"type":{"type":"unknown","name":"{ name: string; avatar: string; memberId: number; }"},"defaultValue":"iGraphUserSchema"},{"id":2165,"name":"version","kind":1024,"kindString":"Property","flags":{},"sources":[{"fileName":"src/nexus/schemas.ts","line":354,"character":4,"url":"https://github.com/toebeann/npc-vortex-api/blob/b51a728/src/nexus/schemas.ts#L354"}],"type":{"type":"intrinsic","name":"string"},"defaultValue":"..."}],"groups":[{"title":"Properties","children":[2158,2168,2167,2169,2161,2163,2170,2171,2162,2164,2159,2160,2166,2172,2173,2174,2165]}],"sources":[{"fileName":"node_modules/.pnpm/zod@3.21.0/node_modules/zod/lib/types.d.ts","line":977,"character":123}]}},{"type":"reflection","declaration":{"id":2175,"name":"__type","kind":65536,"kindString":"Type literal","flags":{},"children":[{"id":2176,"name":"author","kind":1024,"kindString":"Property","flags":{},"sources":[{"fileName":"src/nexus/schemas.ts","line":338,"character":4,"url":"https://github.com/toebeann/npc-vortex-api/blob/b51a728/src/nexus/schemas.ts#L338"}],"type":{"type":"union","types":[{"type":"intrinsic","name":"undefined"},{"type":"intrinsic","name":"string"}]},"defaultValue":"..."},{"id":2186,"name":"category","kind":1024,"kindString":"Property","flags":{},"sources":[{"fileName":"src/nexus/schemas.ts","line":339,"character":4,"url":"https://github.com/toebeann/npc-vortex-api/blob/b51a728/src/nexus/schemas.ts#L339"}],"type":{"type":"intrinsic","name":"string"},"defaultValue":"..."},{"id":2185,"name":"description","kind":1024,"kindString":"Property","flags":{},"sources":[{"fileName":"src/nexus/schemas.ts","line":340,"character":4,"url":"https://github.com/toebeann/npc-vortex-api/blob/b51a728/src/nexus/schemas.ts#L340"}],"type":{"type":"intrinsic","name":"string"},"defaultValue":"..."},{"id":2187,"name":"game","kind":1024,"kindString":"Property","flags":{},"sources":[{"fileName":"src/nexus/schemas.ts","line":341,"character":4,"url":"https://github.com/toebeann/npc-vortex-api/blob/b51a728/src/nexus/schemas.ts#L341"}],"type":{"type":"unknown","name":"{ id?: number | undefined; name?: string | undefined; domainName: string; }"},"defaultValue":"iGameSchema"},{"id":2179,"name":"gameId","kind":1024,"kindString":"Property","flags":{},"sources":[{"fileName":"src/nexus/schemas.ts","line":342,"character":4,"url":"https://github.com/toebeann/npc-vortex-api/blob/b51a728/src/nexus/schemas.ts#L342"}],"type":{"type":"intrinsic","name":"number"},"defaultValue":"..."},{"id":2181,"name":"id","kind":1024,"kindString":"Property","flags":{},"sources":[{"fileName":"src/nexus/schemas.ts","line":343,"character":4,"url":"https://github.com/toebeann/npc-vortex-api/blob/b51a728/src/nexus/schemas.ts#L343"}],"type":{"type":"intrinsic","name":"number"},"defaultValue":"..."},{"id":2188,"name":"ipAddress","kind":1024,"kindString":"Property","flags":{},"sources":[{"fileName":"src/nexus/schemas.ts","line":344,"character":4,"url":"https://github.com/toebeann/npc-vortex-api/blob/b51a728/src/nexus/schemas.ts#L344"}],"type":{"type":"intrinsic","name":"string"},"defaultValue":"..."},{"id":2189,"name":"modCategory","kind":1024,"kindString":"Property","flags":{},"sources":[{"fileName":"src/nexus/schemas.ts","line":345,"character":4,"url":"https://github.com/toebeann/npc-vortex-api/blob/b51a728/src/nexus/schemas.ts#L345"}],"type":{"type":"unknown","name":"{ name: string; category_id: number; parent_category: number | false; }"},"defaultValue":"iModCategorySchema"},{"id":2180,"name":"modId","kind":1024,"kindString":"Property","flags":{},"sources":[{"fileName":"src/nexus/schemas.ts","line":346,"character":4,"url":"https://github.com/toebeann/npc-vortex-api/blob/b51a728/src/nexus/schemas.ts#L346"}],"type":{"type":"intrinsic","name":"number"},"defaultValue":"..."},{"id":2182,"name":"name","kind":1024,"kindString":"Property","flags":{},"sources":[{"fileName":"src/nexus/schemas.ts","line":347,"character":4,"url":"https://github.com/toebeann/npc-vortex-api/blob/b51a728/src/nexus/schemas.ts#L347"}],"type":{"type":"intrinsic","name":"string"},"defaultValue":"..."},{"id":2177,"name":"pictureUrl","kind":1024,"kindString":"Property","flags":{},"sources":[{"fileName":"src/nexus/schemas.ts","line":348,"character":4,"url":"https://github.com/toebeann/npc-vortex-api/blob/b51a728/src/nexus/schemas.ts#L348"}],"type":{"type":"union","types":[{"type":"intrinsic","name":"undefined"},{"type":"intrinsic","name":"string"}]},"defaultValue":"..."},{"id":2178,"name":"status","kind":1024,"kindString":"Property","flags":{},"sources":[{"fileName":"src/nexus/schemas.ts","line":349,"character":4,"url":"https://github.com/toebeann/npc-vortex-api/blob/b51a728/src/nexus/schemas.ts#L349"}],"type":{"type":"intrinsic","name":"string"},"defaultValue":"..."},{"id":2184,"name":"summary","kind":1024,"kindString":"Property","flags":{},"sources":[{"fileName":"src/nexus/schemas.ts","line":350,"character":4,"url":"https://github.com/toebeann/npc-vortex-api/blob/b51a728/src/nexus/schemas.ts#L350"}],"type":{"type":"intrinsic","name":"string"},"defaultValue":"..."},{"id":2190,"name":"trackingData","kind":1024,"kindString":"Property","flags":{},"sources":[{"fileName":"src/nexus/schemas.ts","line":351,"character":4,"url":"https://github.com/toebeann/npc-vortex-api/blob/b51a728/src/nexus/schemas.ts#L351"}],"type":{"type":"unknown","name":"{ test?: number | undefined; }"},"defaultValue":"iTrackingStateSchema"},{"id":2191,"name":"uid","kind":1024,"kindString":"Property","flags":{},"sources":[{"fileName":"src/nexus/schemas.ts","line":352,"character":4,"url":"https://github.com/toebeann/npc-vortex-api/blob/b51a728/src/nexus/schemas.ts#L352"}],"type":{"type":"intrinsic","name":"string"},"defaultValue":"..."},{"id":2192,"name":"uploader","kind":1024,"kindString":"Property","flags":{},"sources":[{"fileName":"src/nexus/schemas.ts","line":353,"character":4,"url":"https://github.com/toebeann/npc-vortex-api/blob/b51a728/src/nexus/schemas.ts#L353"}],"type":{"type":"unknown","name":"{ name: string; avatar: string; memberId: number; }"},"defaultValue":"iGraphUserSchema"},{"id":2183,"name":"version","kind":1024,"kindString":"Property","flags":{},"sources":[{"fileName":"src/nexus/schemas.ts","line":354,"character":4,"url":"https://github.com/toebeann/npc-vortex-api/blob/b51a728/src/nexus/schemas.ts#L354"}],"type":{"type":"intrinsic","name":"string"},"defaultValue":"..."}],"groups":[{"title":"Properties","children":[2176,2186,2185,2187,2179,2181,2188,2189,2180,2182,2177,2178,2184,2190,2191,2192,2183]}],"sources":[{"fileName":"node_modules/.pnpm/zod@3.21.0/node_modules/zod/lib/types.d.ts","line":977,"character":194}]}}],"name":"ZodObject","qualifiedName":"ZodObject","package":"zod"},"defaultValue":"iModSchema"},{"id":2193,"name":"modId","kind":1024,"kindString":"Property","flags":{},"sources":[{"fileName":"src/nexus/schemas.ts","line":366,"character":4,"url":"https://github.com/toebeann/npc-vortex-api/blob/b51a728/src/nexus/schemas.ts#L366"}],"type":{"type":"reference","name":"ZodNumber","qualifiedName":"ZodNumber","package":"zod"},"defaultValue":"..."},{"id":2194,"name":"name","kind":1024,"kindString":"Property","flags":{},"sources":[{"fileName":"src/nexus/schemas.ts","line":367,"character":4,"url":"https://github.com/toebeann/npc-vortex-api/blob/b51a728/src/nexus/schemas.ts#L367"}],"type":{"type":"reference","name":"ZodString","qualifiedName":"ZodString","package":"zod"},"defaultValue":"..."},{"id":2195,"name":"owner","kind":1024,"kindString":"Property","flags":{},"sources":[{"fileName":"src/nexus/schemas.ts","line":368,"character":4,"url":"https://github.com/toebeann/npc-vortex-api/blob/b51a728/src/nexus/schemas.ts#L368"}],"type":{"type":"reference","typeArguments":[{"type":"reflection","declaration":{"id":2196,"name":"__type","kind":65536,"kindString":"Type literal","flags":{},"children":[{"id":2197,"name":"avatar","kind":1024,"kindString":"Property","flags":{},"sources":[{"fileName":"src/nexus/schemas.ts","line":271,"character":4,"url":"https://github.com/toebeann/npc-vortex-api/blob/b51a728/src/nexus/schemas.ts#L271"}],"type":{"type":"reference","name":"ZodString","qualifiedName":"ZodString","package":"zod"},"defaultValue":"..."},{"id":2198,"name":"memberId","kind":1024,"kindString":"Property","flags":{},"sources":[{"fileName":"src/nexus/schemas.ts","line":272,"character":4,"url":"https://github.com/toebeann/npc-vortex-api/blob/b51a728/src/nexus/schemas.ts#L272"}],"type":{"type":"reference","name":"ZodNumber","qualifiedName":"ZodNumber","package":"zod"},"defaultValue":"..."},{"id":2199,"name":"name","kind":1024,"kindString":"Property","flags":{},"sources":[{"fileName":"src/nexus/schemas.ts","line":273,"character":4,"url":"https://github.com/toebeann/npc-vortex-api/blob/b51a728/src/nexus/schemas.ts#L273"}],"type":{"type":"reference","name":"ZodString","qualifiedName":"ZodString","package":"zod"},"defaultValue":"..."}],"groups":[{"title":"Properties","children":[2197,2198,2199]}],"sources":[{"fileName":"src/nexus/schemas.ts","line":270,"character":41,"url":"https://github.com/toebeann/npc-vortex-api/blob/b51a728/src/nexus/schemas.ts#L270"}]}},{"type":"literal","value":"strip"},{"type":"reference","name":"ZodTypeAny","qualifiedName":"ZodTypeAny","package":"zod"},{"type":"reflection","declaration":{"id":2200,"name":"__type","kind":65536,"kindString":"Type literal","flags":{},"children":[{"id":2202,"name":"avatar","kind":1024,"kindString":"Property","flags":{},"sources":[{"fileName":"src/nexus/schemas.ts","line":271,"character":4,"url":"https://github.com/toebeann/npc-vortex-api/blob/b51a728/src/nexus/schemas.ts#L271"}],"type":{"type":"intrinsic","name":"string"},"defaultValue":"..."},{"id":2203,"name":"memberId","kind":1024,"kindString":"Property","flags":{},"sources":[{"fileName":"src/nexus/schemas.ts","line":272,"character":4,"url":"https://github.com/toebeann/npc-vortex-api/blob/b51a728/src/nexus/schemas.ts#L272"}],"type":{"type":"intrinsic","name":"number"},"defaultValue":"..."},{"id":2201,"name":"name","kind":1024,"kindString":"Property","flags":{},"sources":[{"fileName":"src/nexus/schemas.ts","line":273,"character":4,"url":"https://github.com/toebeann/npc-vortex-api/blob/b51a728/src/nexus/schemas.ts#L273"}],"type":{"type":"intrinsic","name":"string"},"defaultValue":"..."}],"groups":[{"title":"Properties","children":[2202,2203,2201]}],"sources":[{"fileName":"node_modules/.pnpm/zod@3.21.0/node_modules/zod/lib/types.d.ts","line":977,"character":123}]}},{"type":"reflection","declaration":{"id":2204,"name":"__type","kind":65536,"kindString":"Type literal","flags":{},"children":[{"id":2206,"name":"avatar","kind":1024,"kindString":"Property","flags":{},"sources":[{"fileName":"src/nexus/schemas.ts","line":271,"character":4,"url":"https://github.com/toebeann/npc-vortex-api/blob/b51a728/src/nexus/schemas.ts#L271"}],"type":{"type":"intrinsic","name":"string"},"defaultValue":"..."},{"id":2207,"name":"memberId","kind":1024,"kindString":"Property","flags":{},"sources":[{"fileName":"src/nexus/schemas.ts","line":272,"character":4,"url":"https://github.com/toebeann/npc-vortex-api/blob/b51a728/src/nexus/schemas.ts#L272"}],"type":{"type":"intrinsic","name":"number"},"defaultValue":"..."},{"id":2205,"name":"name","kind":1024,"kindString":"Property","flags":{},"sources":[{"fileName":"src/nexus/schemas.ts","line":273,"character":4,"url":"https://github.com/toebeann/npc-vortex-api/blob/b51a728/src/nexus/schemas.ts#L273"}],"type":{"type":"intrinsic","name":"string"},"defaultValue":"..."}],"groups":[{"title":"Properties","children":[2206,2207,2205]}],"sources":[{"fileName":"node_modules/.pnpm/zod@3.21.0/node_modules/zod/lib/types.d.ts","line":977,"character":194}]}}],"name":"ZodObject","qualifiedName":"ZodObject","package":"zod"},"defaultValue":"iGraphUserSchema"},{"id":2208,"name":"primary","kind":1024,"kindString":"Property","flags":{},"sources":[{"fileName":"src/nexus/schemas.ts","line":369,"character":4,"url":"https://github.com/toebeann/npc-vortex-api/blob/b51a728/src/nexus/schemas.ts#L369"}],"type":{"type":"reference","name":"ZodNumber","qualifiedName":"ZodNumber","package":"zod"},"defaultValue":"..."},{"id":2209,"name":"reportLink","kind":1024,"kindString":"Property","flags":{},"sources":[{"fileName":"src/nexus/schemas.ts","line":370,"character":4,"url":"https://github.com/toebeann/npc-vortex-api/blob/b51a728/src/nexus/schemas.ts#L370"}],"type":{"type":"reference","name":"ZodString","qualifiedName":"ZodString","package":"zod"},"defaultValue":"..."},{"id":2210,"name":"requirementsAlert","kind":1024,"kindString":"Property","flags":{},"sources":[{"fileName":"src/nexus/schemas.ts","line":371,"character":4,"url":"https://github.com/toebeann/npc-vortex-api/blob/b51a728/src/nexus/schemas.ts#L371"}],"type":{"type":"reference","name":"ZodNumber","qualifiedName":"ZodNumber","package":"zod"},"defaultValue":"..."},{"id":2211,"name":"scanned","kind":1024,"kindString":"Property","flags":{},"sources":[{"fileName":"src/nexus/schemas.ts","line":372,"character":4,"url":"https://github.com/toebeann/npc-vortex-api/blob/b51a728/src/nexus/schemas.ts#L372"}],"type":{"type":"reference","name":"ZodNumber","qualifiedName":"ZodNumber","package":"zod"},"defaultValue":"..."},{"id":2212,"name":"size","kind":1024,"kindString":"Property","flags":{},"sources":[{"fileName":"src/nexus/schemas.ts","line":373,"character":4,"url":"https://github.com/toebeann/npc-vortex-api/blob/b51a728/src/nexus/schemas.ts#L373"}],"type":{"type":"reference","name":"ZodNumber","qualifiedName":"ZodNumber","package":"zod"},"defaultValue":"..."},{"id":2213,"name":"sizeInBytes","kind":1024,"kindString":"Property","flags":{},"sources":[{"fileName":"src/nexus/schemas.ts","line":374,"character":4,"url":"https://github.com/toebeann/npc-vortex-api/blob/b51a728/src/nexus/schemas.ts#L374"}],"type":{"type":"reference","typeArguments":[{"type":"reference","name":"ZodString","qualifiedName":"ZodString","package":"zod"}],"name":"ZodOptional","qualifiedName":"ZodOptional","package":"zod"},"defaultValue":"..."},{"id":2214,"name":"uCount","kind":1024,"kindString":"Property","flags":{},"sources":[{"fileName":"src/nexus/schemas.ts","line":375,"character":4,"url":"https://github.com/toebeann/npc-vortex-api/blob/b51a728/src/nexus/schemas.ts#L375"}],"type":{"type":"reference","name":"ZodNumber","qualifiedName":"ZodNumber","package":"zod"},"defaultValue":"..."},{"id":2215,"name":"uid","kind":1024,"kindString":"Property","flags":{},"sources":[{"fileName":"src/nexus/schemas.ts","line":376,"character":4,"url":"https://github.com/toebeann/npc-vortex-api/blob/b51a728/src/nexus/schemas.ts#L376"}],"type":{"type":"reference","name":"ZodString","qualifiedName":"ZodString","package":"zod"},"defaultValue":"..."},{"id":2216,"name":"uri","kind":1024,"kindString":"Property","flags":{},"sources":[{"fileName":"src/nexus/schemas.ts","line":377,"character":4,"url":"https://github.com/toebeann/npc-vortex-api/blob/b51a728/src/nexus/schemas.ts#L377"}],"type":{"type":"reference","name":"ZodString","qualifiedName":"ZodString","package":"zod"},"defaultValue":"..."},{"id":2217,"name":"version","kind":1024,"kindString":"Property","flags":{},"sources":[{"fileName":"src/nexus/schemas.ts","line":378,"character":4,"url":"https://github.com/toebeann/npc-vortex-api/blob/b51a728/src/nexus/schemas.ts#L378"}],"type":{"type":"reference","name":"ZodString","qualifiedName":"ZodString","package":"zod"},"defaultValue":"..."}],"groups":[{"title":"Properties","children":[2077,2078,2079,2080,2081,2082,2095,2096,2193,2194,2195,2208,2209,2210,2211,2212,2213,2214,2215,2216,2217]}],"sources":[{"fileName":"src/nexus/schemas.ts","line":357,"character":39,"url":"https://github.com/toebeann/npc-vortex-api/blob/b51a728/src/nexus/schemas.ts#L357"}]}},{"type":"literal","value":"strip"},{"type":"reference","name":"ZodTypeAny","qualifiedName":"ZodTypeAny","package":"zod"},{"type":"reflection","declaration":{"id":2218,"name":"__type","kind":65536,"kindString":"Type literal","flags":{},"children":[{"id":2231,"name":"categoryId","kind":1024,"kindString":"Property","flags":{},"sources":[{"fileName":"src/nexus/schemas.ts","line":358,"character":4,"url":"https://github.com/toebeann/npc-vortex-api/blob/b51a728/src/nexus/schemas.ts#L358"}],"type":{"type":"intrinsic","name":"number"},"defaultValue":"..."},{"id":2223,"name":"count","kind":1024,"kindString":"Property","flags":{},"sources":[{"fileName":"src/nexus/schemas.ts","line":359,"character":4,"url":"https://github.com/toebeann/npc-vortex-api/blob/b51a728/src/nexus/schemas.ts#L359"}],"type":{"type":"intrinsic","name":"number"},"defaultValue":"..."},{"id":2222,"name":"date","kind":1024,"kindString":"Property","flags":{},"sources":[{"fileName":"src/nexus/schemas.ts","line":360,"character":4,"url":"https://github.com/toebeann/npc-vortex-api/blob/b51a728/src/nexus/schemas.ts#L360"}],"type":{"type":"intrinsic","name":"number"},"defaultValue":"..."},{"id":2226,"name":"description","kind":1024,"kindString":"Property","flags":{},"sources":[{"fileName":"src/nexus/schemas.ts","line":361,"character":4,"url":"https://github.com/toebeann/npc-vortex-api/blob/b51a728/src/nexus/schemas.ts#L361"}],"type":{"type":"intrinsic","name":"string"},"defaultValue":"..."},{"id":2221,"name":"fileId","kind":1024,"kindString":"Property","flags":{},"sources":[{"fileName":"src/nexus/schemas.ts","line":362,"character":4,"url":"https://github.com/toebeann/npc-vortex-api/blob/b51a728/src/nexus/schemas.ts#L362"}],"type":{"type":"intrinsic","name":"number"},"defaultValue":"..."},{"id":2229,"name":"game","kind":1024,"kindString":"Property","flags":{},"sources":[{"fileName":"src/nexus/schemas.ts","line":363,"character":4,"url":"https://github.com/toebeann/npc-vortex-api/blob/b51a728/src/nexus/schemas.ts#L363"}],"type":{"type":"unknown","name":"{ id?: number | undefined; name?: string | undefined; domainName: string; }"},"defaultValue":"iGameSchema"},{"id":2232,"name":"manager","kind":1024,"kindString":"Property","flags":{},"sources":[{"fileName":"src/nexus/schemas.ts","line":364,"character":4,"url":"https://github.com/toebeann/npc-vortex-api/blob/b51a728/src/nexus/schemas.ts#L364"}],"type":{"type":"intrinsic","name":"number"},"defaultValue":"..."},{"id":2228,"name":"mod","kind":1024,"kindString":"Property","flags":{},"sources":[{"fileName":"src/nexus/schemas.ts","line":365,"character":4,"url":"https://github.com/toebeann/npc-vortex-api/blob/b51a728/src/nexus/schemas.ts#L365"}],"type":{"type":"unknown","name":"{ author?: string | undefined; pictureUrl?: string | undefined; status: string; gameId: number; modId: number; id: number; name: string; version: string; summary: string; description: string; category: string; ... 5 more ...; uploader: { ...; }; }"},"defaultValue":"iModSchema"},{"id":2220,"name":"modId","kind":1024,"kindString":"Property","flags":{},"sources":[{"fileName":"src/nexus/schemas.ts","line":366,"character":4,"url":"https://github.com/toebeann/npc-vortex-api/blob/b51a728/src/nexus/schemas.ts#L366"}],"type":{"type":"intrinsic","name":"number"},"defaultValue":"..."},{"id":2224,"name":"name","kind":1024,"kindString":"Property","flags":{},"sources":[{"fileName":"src/nexus/schemas.ts","line":367,"character":4,"url":"https://github.com/toebeann/npc-vortex-api/blob/b51a728/src/nexus/schemas.ts#L367"}],"type":{"type":"intrinsic","name":"string"},"defaultValue":"..."},{"id":2233,"name":"owner","kind":1024,"kindString":"Property","flags":{},"sources":[{"fileName":"src/nexus/schemas.ts","line":368,"character":4,"url":"https://github.com/toebeann/npc-vortex-api/blob/b51a728/src/nexus/schemas.ts#L368"}],"type":{"type":"unknown","name":"{ name: string; avatar: string; memberId: number; }"},"defaultValue":"iGraphUserSchema"},{"id":2234,"name":"primary","kind":1024,"kindString":"Property","flags":{},"sources":[{"fileName":"src/nexus/schemas.ts","line":369,"character":4,"url":"https://github.com/toebeann/npc-vortex-api/blob/b51a728/src/nexus/schemas.ts#L369"}],"type":{"type":"intrinsic","name":"number"},"defaultValue":"..."},{"id":2235,"name":"reportLink","kind":1024,"kindString":"Property","flags":{},"sources":[{"fileName":"src/nexus/schemas.ts","line":370,"character":4,"url":"https://github.com/toebeann/npc-vortex-api/blob/b51a728/src/nexus/schemas.ts#L370"}],"type":{"type":"intrinsic","name":"string"},"defaultValue":"..."},{"id":2236,"name":"requirementsAlert","kind":1024,"kindString":"Property","flags":{},"sources":[{"fileName":"src/nexus/schemas.ts","line":371,"character":4,"url":"https://github.com/toebeann/npc-vortex-api/blob/b51a728/src/nexus/schemas.ts#L371"}],"type":{"type":"intrinsic","name":"number"},"defaultValue":"..."},{"id":2237,"name":"scanned","kind":1024,"kindString":"Property","flags":{},"sources":[{"fileName":"src/nexus/schemas.ts","line":372,"character":4,"url":"https://github.com/toebeann/npc-vortex-api/blob/b51a728/src/nexus/schemas.ts#L372"}],"type":{"type":"intrinsic","name":"number"},"defaultValue":"..."},{"id":2227,"name":"size","kind":1024,"kindString":"Property","flags":{},"sources":[{"fileName":"src/nexus/schemas.ts","line":373,"character":4,"url":"https://github.com/toebeann/npc-vortex-api/blob/b51a728/src/nexus/schemas.ts#L373"}],"type":{"type":"intrinsic","name":"number"},"defaultValue":"..."},{"id":2219,"name":"sizeInBytes","kind":1024,"kindString":"Property","flags":{},"sources":[{"fileName":"src/nexus/schemas.ts","line":374,"character":4,"url":"https://github.com/toebeann/npc-vortex-api/blob/b51a728/src/nexus/schemas.ts#L374"}],"type":{"type":"union","types":[{"type":"intrinsic","name":"undefined"},{"type":"intrinsic","name":"string"}]},"defaultValue":"..."},{"id":2238,"name":"uCount","kind":1024,"kindString":"Property","flags":{},"sources":[{"fileName":"src/nexus/schemas.ts","line":375,"character":4,"url":"https://github.com/toebeann/npc-vortex-api/blob/b51a728/src/nexus/schemas.ts#L375"}],"type":{"type":"intrinsic","name":"number"},"defaultValue":"..."},{"id":2230,"name":"uid","kind":1024,"kindString":"Property","flags":{},"sources":[{"fileName":"src/nexus/schemas.ts","line":376,"character":4,"url":"https://github.com/toebeann/npc-vortex-api/blob/b51a728/src/nexus/schemas.ts#L376"}],"type":{"type":"intrinsic","name":"string"},"defaultValue":"..."},{"id":2239,"name":"uri","kind":1024,"kindString":"Property","flags":{},"sources":[{"fileName":"src/nexus/schemas.ts","line":377,"character":4,"url":"https://github.com/toebeann/npc-vortex-api/blob/b51a728/src/nexus/schemas.ts#L377"}],"type":{"type":"intrinsic","name":"string"},"defaultValue":"..."},{"id":2225,"name":"version","kind":1024,"kindString":"Property","flags":{},"sources":[{"fileName":"src/nexus/schemas.ts","line":378,"character":4,"url":"https://github.com/toebeann/npc-vortex-api/blob/b51a728/src/nexus/schemas.ts#L378"}],"type":{"type":"intrinsic","name":"string"},"defaultValue":"..."}],"groups":[{"title":"Properties","children":[2231,2223,2222,2226,2221,2229,2232,2228,2220,2224,2233,2234,2235,2236,2237,2227,2219,2238,2230,2239,2225]}],"sources":[{"fileName":"node_modules/.pnpm/zod@3.21.0/node_modules/zod/lib/types.d.ts","line":977,"character":123}]}},{"type":"reflection","declaration":{"id":2240,"name":"__type","kind":65536,"kindString":"Type literal","flags":{},"children":[{"id":2253,"name":"categoryId","kind":1024,"kindString":"Property","flags":{},"sources":[{"fileName":"src/nexus/schemas.ts","line":358,"character":4,"url":"https://github.com/toebeann/npc-vortex-api/blob/b51a728/src/nexus/schemas.ts#L358"}],"type":{"type":"intrinsic","name":"number"},"defaultValue":"..."},{"id":2245,"name":"count","kind":1024,"kindString":"Property","flags":{},"sources":[{"fileName":"src/nexus/schemas.ts","line":359,"character":4,"url":"https://github.com/toebeann/npc-vortex-api/blob/b51a728/src/nexus/schemas.ts#L359"}],"type":{"type":"intrinsic","name":"number"},"defaultValue":"..."},{"id":2244,"name":"date","kind":1024,"kindString":"Property","flags":{},"sources":[{"fileName":"src/nexus/schemas.ts","line":360,"character":4,"url":"https://github.com/toebeann/npc-vortex-api/blob/b51a728/src/nexus/schemas.ts#L360"}],"type":{"type":"intrinsic","name":"number"},"defaultValue":"..."},{"id":2248,"name":"description","kind":1024,"kindString":"Property","flags":{},"sources":[{"fileName":"src/nexus/schemas.ts","line":361,"character":4,"url":"https://github.com/toebeann/npc-vortex-api/blob/b51a728/src/nexus/schemas.ts#L361"}],"type":{"type":"intrinsic","name":"string"},"defaultValue":"..."},{"id":2243,"name":"fileId","kind":1024,"kindString":"Property","flags":{},"sources":[{"fileName":"src/nexus/schemas.ts","line":362,"character":4,"url":"https://github.com/toebeann/npc-vortex-api/blob/b51a728/src/nexus/schemas.ts#L362"}],"type":{"type":"intrinsic","name":"number"},"defaultValue":"..."},{"id":2251,"name":"game","kind":1024,"kindString":"Property","flags":{},"sources":[{"fileName":"src/nexus/schemas.ts","line":363,"character":4,"url":"https://github.com/toebeann/npc-vortex-api/blob/b51a728/src/nexus/schemas.ts#L363"}],"type":{"type":"unknown","name":"{ id?: number | undefined; name?: string | undefined; domainName: string; }"},"defaultValue":"iGameSchema"},{"id":2254,"name":"manager","kind":1024,"kindString":"Property","flags":{},"sources":[{"fileName":"src/nexus/schemas.ts","line":364,"character":4,"url":"https://github.com/toebeann/npc-vortex-api/blob/b51a728/src/nexus/schemas.ts#L364"}],"type":{"type":"intrinsic","name":"number"},"defaultValue":"..."},{"id":2250,"name":"mod","kind":1024,"kindString":"Property","flags":{},"sources":[{"fileName":"src/nexus/schemas.ts","line":365,"character":4,"url":"https://github.com/toebeann/npc-vortex-api/blob/b51a728/src/nexus/schemas.ts#L365"}],"type":{"type":"unknown","name":"{ author?: string | undefined; pictureUrl?: string | undefined; status: string; gameId: number; modId: number; id: number; name: string; version: string; summary: string; description: string; category: string; ... 5 more ...; uploader: { ...; }; }"},"defaultValue":"iModSchema"},{"id":2242,"name":"modId","kind":1024,"kindString":"Property","flags":{},"sources":[{"fileName":"src/nexus/schemas.ts","line":366,"character":4,"url":"https://github.com/toebeann/npc-vortex-api/blob/b51a728/src/nexus/schemas.ts#L366"}],"type":{"type":"intrinsic","name":"number"},"defaultValue":"..."},{"id":2246,"name":"name","kind":1024,"kindString":"Property","flags":{},"sources":[{"fileName":"src/nexus/schemas.ts","line":367,"character":4,"url":"https://github.com/toebeann/npc-vortex-api/blob/b51a728/src/nexus/schemas.ts#L367"}],"type":{"type":"intrinsic","name":"string"},"defaultValue":"..."},{"id":2255,"name":"owner","kind":1024,"kindString":"Property","flags":{},"sources":[{"fileName":"src/nexus/schemas.ts","line":368,"character":4,"url":"https://github.com/toebeann/npc-vortex-api/blob/b51a728/src/nexus/schemas.ts#L368"}],"type":{"type":"unknown","name":"{ name: string; avatar: string; memberId: number; }"},"defaultValue":"iGraphUserSchema"},{"id":2256,"name":"primary","kind":1024,"kindString":"Property","flags":{},"sources":[{"fileName":"src/nexus/schemas.ts","line":369,"character":4,"url":"https://github.com/toebeann/npc-vortex-api/blob/b51a728/src/nexus/schemas.ts#L369"}],"type":{"type":"intrinsic","name":"number"},"defaultValue":"..."},{"id":2257,"name":"reportLink","kind":1024,"kindString":"Property","flags":{},"sources":[{"fileName":"src/nexus/schemas.ts","line":370,"character":4,"url":"https://github.com/toebeann/npc-vortex-api/blob/b51a728/src/nexus/schemas.ts#L370"}],"type":{"type":"intrinsic","name":"string"},"defaultValue":"..."},{"id":2258,"name":"requirementsAlert","kind":1024,"kindString":"Property","flags":{},"sources":[{"fileName":"src/nexus/schemas.ts","line":371,"character":4,"url":"https://github.com/toebeann/npc-vortex-api/blob/b51a728/src/nexus/schemas.ts#L371"}],"type":{"type":"intrinsic","name":"number"},"defaultValue":"..."},{"id":2259,"name":"scanned","kind":1024,"kindString":"Property","flags":{},"sources":[{"fileName":"src/nexus/schemas.ts","line":372,"character":4,"url":"https://github.com/toebeann/npc-vortex-api/blob/b51a728/src/nexus/schemas.ts#L372"}],"type":{"type":"intrinsic","name":"number"},"defaultValue":"..."},{"id":2249,"name":"size","kind":1024,"kindString":"Property","flags":{},"sources":[{"fileName":"src/nexus/schemas.ts","line":373,"character":4,"url":"https://github.com/toebeann/npc-vortex-api/blob/b51a728/src/nexus/schemas.ts#L373"}],"type":{"type":"intrinsic","name":"number"},"defaultValue":"..."},{"id":2241,"name":"sizeInBytes","kind":1024,"kindString":"Property","flags":{},"sources":[{"fileName":"src/nexus/schemas.ts","line":374,"character":4,"url":"https://github.com/toebeann/npc-vortex-api/blob/b51a728/src/nexus/schemas.ts#L374"}],"type":{"type":"union","types":[{"type":"intrinsic","name":"undefined"},{"type":"intrinsic","name":"string"}]},"defaultValue":"..."},{"id":2260,"name":"uCount","kind":1024,"kindString":"Property","flags":{},"sources":[{"fileName":"src/nexus/schemas.ts","line":375,"character":4,"url":"https://github.com/toebeann/npc-vortex-api/blob/b51a728/src/nexus/schemas.ts#L375"}],"type":{"type":"intrinsic","name":"number"},"defaultValue":"..."},{"id":2252,"name":"uid","kind":1024,"kindString":"Property","flags":{},"sources":[{"fileName":"src/nexus/schemas.ts","line":376,"character":4,"url":"https://github.com/toebeann/npc-vortex-api/blob/b51a728/src/nexus/schemas.ts#L376"}],"type":{"type":"intrinsic","name":"string"},"defaultValue":"..."},{"id":2261,"name":"uri","kind":1024,"kindString":"Property","flags":{},"sources":[{"fileName":"src/nexus/schemas.ts","line":377,"character":4,"url":"https://github.com/toebeann/npc-vortex-api/blob/b51a728/src/nexus/schemas.ts#L377"}],"type":{"type":"intrinsic","name":"string"},"defaultValue":"..."},{"id":2247,"name":"version","kind":1024,"kindString":"Property","flags":{},"sources":[{"fileName":"src/nexus/schemas.ts","line":378,"character":4,"url":"https://github.com/toebeann/npc-vortex-api/blob/b51a728/src/nexus/schemas.ts#L378"}],"type":{"type":"intrinsic","name":"string"},"defaultValue":"..."}],"groups":[{"title":"Properties","children":[2253,2245,2244,2248,2243,2251,2254,2250,2242,2246,2255,2256,2257,2258,2259,2249,2241,2260,2252,2261,2247]}],"sources":[{"fileName":"node_modules/.pnpm/zod@3.21.0/node_modules/zod/lib/types.d.ts","line":977,"character":194}]}}],"name":"ZodObject","qualifiedName":"ZodObject","package":"zod"}],"name":"ZodOptional","qualifiedName":"ZodOptional","package":"zod"},"defaultValue":"..."},{"id":2262,"name":"fileId","kind":1024,"kindString":"Property","flags":{},"sources":[{"fileName":"src/nexus/schemas.ts","line":384,"character":4,"url":"https://github.com/toebeann/npc-vortex-api/blob/b51a728/src/nexus/schemas.ts#L384"}],"type":{"type":"reference","name":"ZodNumber","qualifiedName":"ZodNumber","package":"zod"},"defaultValue":"..."},{"id":2263,"name":"gameId","kind":1024,"kindString":"Property","flags":{},"sources":[{"fileName":"src/nexus/schemas.ts","line":385,"character":4,"url":"https://github.com/toebeann/npc-vortex-api/blob/b51a728/src/nexus/schemas.ts#L385"}],"type":{"type":"reference","name":"ZodNumber","qualifiedName":"ZodNumber","package":"zod"},"defaultValue":"..."},{"id":2264,"name":"id","kind":1024,"kindString":"Property","flags":{},"sources":[{"fileName":"src/nexus/schemas.ts","line":386,"character":4,"url":"https://github.com/toebeann/npc-vortex-api/blob/b51a728/src/nexus/schemas.ts#L386"}],"type":{"type":"reference","name":"ZodNumber","qualifiedName":"ZodNumber","package":"zod"},"defaultValue":"..."},{"id":2265,"name":"optional","kind":1024,"kindString":"Property","flags":{},"sources":[{"fileName":"src/nexus/schemas.ts","line":387,"character":4,"url":"https://github.com/toebeann/npc-vortex-api/blob/b51a728/src/nexus/schemas.ts#L387"}],"type":{"type":"reference","name":"ZodBoolean","qualifiedName":"ZodBoolean","package":"zod"},"defaultValue":"..."},{"id":2266,"name":"updatePolicy","kind":1024,"kindString":"Property","flags":{},"sources":[{"fileName":"src/nexus/schemas.ts","line":388,"character":4,"url":"https://github.com/toebeann/npc-vortex-api/blob/b51a728/src/nexus/schemas.ts#L388"}],"type":{"type":"reference","name":"ZodString","qualifiedName":"ZodString","package":"zod"},"defaultValue":"..."},{"id":2267,"name":"version","kind":1024,"kindString":"Property","flags":{},"sources":[{"fileName":"src/nexus/schemas.ts","line":389,"character":4,"url":"https://github.com/toebeann/npc-vortex-api/blob/b51a728/src/nexus/schemas.ts#L389"}],"type":{"type":"reference","name":"ZodString","qualifiedName":"ZodString","package":"zod"},"defaultValue":"..."}],"groups":[{"title":"Properties","children":[2074,2075,2262,2263,2264,2265,2266,2267]}],"sources":[{"fileName":"src/nexus/schemas.ts","line":381,"character":53,"url":"https://github.com/toebeann/npc-vortex-api/blob/b51a728/src/nexus/schemas.ts#L381"}]}},{"type":"literal","value":"strip"},{"type":"reference","name":"ZodTypeAny","qualifiedName":"ZodTypeAny","package":"zod"},{"type":"reflection","declaration":{"id":2268,"name":"__type","kind":65536,"kindString":"Type literal","flags":{},"children":[{"id":2274,"name":"collectionRevisionId","kind":1024,"kindString":"Property","flags":{},"sources":[{"fileName":"src/nexus/schemas.ts","line":382,"character":4,"url":"https://github.com/toebeann/npc-vortex-api/blob/b51a728/src/nexus/schemas.ts#L382"}],"type":{"type":"intrinsic","name":"number"},"defaultValue":"..."},{"id":2269,"name":"file","kind":1024,"kindString":"Property","flags":{},"sources":[{"fileName":"src/nexus/schemas.ts","line":383,"character":4,"url":"https://github.com/toebeann/npc-vortex-api/blob/b51a728/src/nexus/schemas.ts#L383"}],"type":{"type":"union","types":[{"type":"intrinsic","name":"undefined"},{"type":"unknown","name":"{ sizeInBytes?: string | undefined; modId: number; fileId: number; date: number; count: number; name: string; version: string; description: string; size: number; mod: { author?: string | undefined; ... 15 more ...; uploader: { ...; }; }; ... 10 more ...; uri: string; }"}]},"defaultValue":"..."},{"id":2271,"name":"fileId","kind":1024,"kindString":"Property","flags":{},"sources":[{"fileName":"src/nexus/schemas.ts","line":384,"character":4,"url":"https://github.com/toebeann/npc-vortex-api/blob/b51a728/src/nexus/schemas.ts#L384"}],"type":{"type":"intrinsic","name":"number"},"defaultValue":"..."},{"id":2270,"name":"gameId","kind":1024,"kindString":"Property","flags":{},"sources":[{"fileName":"src/nexus/schemas.ts","line":385,"character":4,"url":"https://github.com/toebeann/npc-vortex-api/blob/b51a728/src/nexus/schemas.ts#L385"}],"type":{"type":"intrinsic","name":"number"},"defaultValue":"..."},{"id":2272,"name":"id","kind":1024,"kindString":"Property","flags":{},"sources":[{"fileName":"src/nexus/schemas.ts","line":386,"character":4,"url":"https://github.com/toebeann/npc-vortex-api/blob/b51a728/src/nexus/schemas.ts#L386"}],"type":{"type":"intrinsic","name":"number"},"defaultValue":"..."},{"id":2275,"name":"optional","kind":1024,"kindString":"Property","flags":{},"sources":[{"fileName":"src/nexus/schemas.ts","line":387,"character":4,"url":"https://github.com/toebeann/npc-vortex-api/blob/b51a728/src/nexus/schemas.ts#L387"}],"type":{"type":"intrinsic","name":"boolean"},"defaultValue":"..."},{"id":2276,"name":"updatePolicy","kind":1024,"kindString":"Property","flags":{},"sources":[{"fileName":"src/nexus/schemas.ts","line":388,"character":4,"url":"https://github.com/toebeann/npc-vortex-api/blob/b51a728/src/nexus/schemas.ts#L388"}],"type":{"type":"intrinsic","name":"string"},"defaultValue":"..."},{"id":2273,"name":"version","kind":1024,"kindString":"Property","flags":{},"sources":[{"fileName":"src/nexus/schemas.ts","line":389,"character":4,"url":"https://github.com/toebeann/npc-vortex-api/blob/b51a728/src/nexus/schemas.ts#L389"}],"type":{"type":"intrinsic","name":"string"},"defaultValue":"..."}],"groups":[{"title":"Properties","children":[2274,2269,2271,2270,2272,2275,2276,2273]}],"sources":[{"fileName":"node_modules/.pnpm/zod@3.21.0/node_modules/zod/lib/types.d.ts","line":977,"character":123}]}},{"type":"reflection","declaration":{"id":2277,"name":"__type","kind":65536,"kindString":"Type literal","flags":{},"children":[{"id":2283,"name":"collectionRevisionId","kind":1024,"kindString":"Property","flags":{},"sources":[{"fileName":"src/nexus/schemas.ts","line":382,"character":4,"url":"https://github.com/toebeann/npc-vortex-api/blob/b51a728/src/nexus/schemas.ts#L382"}],"type":{"type":"intrinsic","name":"number"},"defaultValue":"..."},{"id":2278,"name":"file","kind":1024,"kindString":"Property","flags":{},"sources":[{"fileName":"src/nexus/schemas.ts","line":383,"character":4,"url":"https://github.com/toebeann/npc-vortex-api/blob/b51a728/src/nexus/schemas.ts#L383"}],"type":{"type":"union","types":[{"type":"intrinsic","name":"undefined"},{"type":"unknown","name":"{ sizeInBytes?: string | undefined; modId: number; fileId: number; date: number; count: number; name: string; version: string; description: string; size: number; mod: { author?: string | undefined; ... 15 more ...; uploader: { ...; }; }; ... 10 more ...; uri: string; }"}]},"defaultValue":"..."},{"id":2280,"name":"fileId","kind":1024,"kindString":"Property","flags":{},"sources":[{"fileName":"src/nexus/schemas.ts","line":384,"character":4,"url":"https://github.com/toebeann/npc-vortex-api/blob/b51a728/src/nexus/schemas.ts#L384"}],"type":{"type":"intrinsic","name":"number"},"defaultValue":"..."},{"id":2279,"name":"gameId","kind":1024,"kindString":"Property","flags":{},"sources":[{"fileName":"src/nexus/schemas.ts","line":385,"character":4,"url":"https://github.com/toebeann/npc-vortex-api/blob/b51a728/src/nexus/schemas.ts#L385"}],"type":{"type":"intrinsic","name":"number"},"defaultValue":"..."},{"id":2281,"name":"id","kind":1024,"kindString":"Property","flags":{},"sources":[{"fileName":"src/nexus/schemas.ts","line":386,"character":4,"url":"https://github.com/toebeann/npc-vortex-api/blob/b51a728/src/nexus/schemas.ts#L386"}],"type":{"type":"intrinsic","name":"number"},"defaultValue":"..."},{"id":2284,"name":"optional","kind":1024,"kindString":"Property","flags":{},"sources":[{"fileName":"src/nexus/schemas.ts","line":387,"character":4,"url":"https://github.com/toebeann/npc-vortex-api/blob/b51a728/src/nexus/schemas.ts#L387"}],"type":{"type":"intrinsic","name":"boolean"},"defaultValue":"..."},{"id":2285,"name":"updatePolicy","kind":1024,"kindString":"Property","flags":{},"sources":[{"fileName":"src/nexus/schemas.ts","line":388,"character":4,"url":"https://github.com/toebeann/npc-vortex-api/blob/b51a728/src/nexus/schemas.ts#L388"}],"type":{"type":"intrinsic","name":"string"},"defaultValue":"..."},{"id":2282,"name":"version","kind":1024,"kindString":"Property","flags":{},"sources":[{"fileName":"src/nexus/schemas.ts","line":389,"character":4,"url":"https://github.com/toebeann/npc-vortex-api/blob/b51a728/src/nexus/schemas.ts#L389"}],"type":{"type":"intrinsic","name":"string"},"defaultValue":"..."}],"groups":[{"title":"Properties","children":[2283,2278,2280,2279,2281,2284,2285,2282]}],"sources":[{"fileName":"node_modules/.pnpm/zod@3.21.0/node_modules/zod/lib/types.d.ts","line":977,"character":194}]}}],"name":"ZodObject","qualifiedName":"ZodObject","package":"zod"},"defaultValue":"...","is":{"declaration":true},"location":{"query":"nexus.schemas.Variable.iCollectionRevisionModSchema","hash":""},"text":{},"parentId":555}
