{"id":3181,"name":"getCollection","kind":64,"kindString":"Function","flags":{},"children":[],"sources":[{"fileName":"src/nexus/index.ts","fullFileName":"/home/runner/work/npc-vortex-api/npc-vortex-api/src/nexus/index.ts","line":65,"character":13,"url":"https://github.com/toebeann/npc-vortex-api/blob/b51a728/src/nexus/index.ts#L65"}],"signatures":[{"id":3182,"name":"getCollection","kind":4096,"kindString":"Call signature","flags":{},"comment":{"summary":[{"kind":"text","text":"Retrieves details about a collection."}],"blockTags":[{"tag":"@returns","content":[{"kind":"text","text":"A "},{"kind":"inline-tag","tag":"@link","text":"Promise","target":"https://developer.mozilla.org/en-US/docs/Web/JavaScript/Reference/Global_Objects/Promise"},{"kind":"text","text":" which when resolved, passes the response from the Nexus Mods API to its "},{"kind":"inline-tag","tag":"@link","text":"then","target":"https://developer.mozilla.org/en-US/docs/Web/JavaScript/Reference/Global_Objects/Promise/then"},{"kind":"text","text":" handler(s)."}]},{"tag":"@see","content":[{"kind":"inline-tag","tag":"@link","text":"https://toebeann.github.io/npc-vortex-api/stable/?page=nexus.Function.getCollection","target":"https://toebeann.github.io/npc-vortex-api/stable/?page=nexus.Function.getCollection"}]}]},"parameters":[{"id":3183,"name":"options","kind":32768,"kindString":"Parameter","flags":{},"type":{"type":"reflection","declaration":{"id":3184,"name":"__type","kind":65536,"kindString":"Type literal","flags":{},"children":[{"id":3185,"name":"input","kind":1024,"kindString":"Property","flags":{},"sources":[{"fileName":"src/nexus/index.ts","line":66,"character":4,"url":"https://github.com/toebeann/npc-vortex-api/blob/b51a728/src/nexus/index.ts#L66"}],"type":{"type":"reflection","declaration":{"id":3186,"name":"__type","kind":65536,"kindString":"Type literal","flags":{},"children":[{"id":3187,"name":"slug","kind":1024,"kindString":"Property","flags":{},"sources":[{"fileName":"src/nexus/index.ts","line":66,"character":13,"url":"https://github.com/toebeann/npc-vortex-api/blob/b51a728/src/nexus/index.ts#L66"}],"type":{"type":"intrinsic","name":"string"}}],"groups":[{"title":"Properties","children":[3187]}],"sources":[{"fileName":"src/nexus/index.ts","line":66,"character":11,"url":"https://github.com/toebeann/npc-vortex-api/blob/b51a728/src/nexus/index.ts#L66"}]}}},{"id":3188,"name":"signal","kind":1024,"kindString":"Property","flags":{"isOptional":true},"sources":[{"fileName":"src/nexus/index.ts","line":67,"character":4,"url":"https://github.com/toebeann/npc-vortex-api/blob/b51a728/src/nexus/index.ts#L67"}],"type":{"type":"reference","name":"AbortSignal","qualifiedName":"AbortSignal","package":"@types/node"}}],"groups":[{"title":"Properties","children":[3185,3188]}],"sources":[{"fileName":"src/nexus/index.ts","line":65,"character":45,"url":"https://github.com/toebeann/npc-vortex-api/blob/b51a728/src/nexus/index.ts#L65"}]}},"text":{}}],"type":{"type":"reference","typeArguments":[{"type":"reference","id":2901,"name":"ICollection"}],"name":"Promise","qualifiedName":"Promise","package":"typescript"},"is":{"declaration":false},"location":{"query":"nexus.Function.getCollection","hash":"getCollection"},"text":{"comment":"<p>Retrieves details about a collection.</p>\n<h5>Returns:</h5><p>A <a href=\"https://developer.mozilla.org/en-US/docs/Web/JavaScript/Reference/Global_Objects/Promise\">Promise</a> which when resolved, passes the response from the Nexus Mods API to its <a href=\"https://developer.mozilla.org/en-US/docs/Web/JavaScript/Reference/Global_Objects/Promise/then\">then</a> handler(s).</p>\n<h5>See:</h5><p><a href=\"https://toebeann.github.io/npc-vortex-api/stable/?page=nexus.Function.getCollection\">https://toebeann.github.io/npc-vortex-api/stable/?page=nexus.Function.getCollection</a></p>\n"},"sources":[{"fileName":"src/nexus/index.ts","fullFileName":"/home/runner/work/npc-vortex-api/npc-vortex-api/src/nexus/index.ts","line":65,"character":29,"url":"https://github.com/toebeann/npc-vortex-api/blob/b51a728/src/nexus/index.ts#L65"}],"parentId":3181}],"is":{"declaration":true},"location":{"query":"nexus.Function.getCollection","hash":""},"text":{},"parentId":554}
