{"id":1327,"name":"iGameInfoSchema","kind":32,"kindString":"Variable","flags":{"isConst":true},"children":[],"sources":[{"fileName":"src/nexus/schemas.ts","fullFileName":"/home/runner/work/npc-vortex-api/npc-vortex-api/src/nexus/schemas.ts","line":194,"character":13,"url":"https://github.com/toebeann/npc-vortex-api/blob/b51a728/src/nexus/schemas.ts#L194"}],"type":{"type":"reference","typeArguments":[{"type":"reflection","declaration":{"id":1328,"name":"__type","kind":65536,"kindString":"Type literal","flags":{},"children":[{"id":1338,"name":"approved_date","kind":1024,"kindString":"Property","flags":{},"sources":[{"fileName":"src/nexus/schemas.ts","line":185,"character":4,"url":"https://github.com/toebeann/npc-vortex-api/blob/b51a728/src/nexus/schemas.ts#L185"}],"type":{"type":"reference","name":"ZodNumber","qualifiedName":"ZodNumber","package":"zod"},"defaultValue":"..."},{"id":1339,"name":"categories","kind":1024,"kindString":"Property","flags":{},"sources":[{"fileName":"src/nexus/schemas.ts","line":195,"character":4,"url":"https://github.com/toebeann/npc-vortex-api/blob/b51a728/src/nexus/schemas.ts#L195"}],"type":{"type":"reference","typeArguments":[{"type":"reference","typeArguments":[{"type":"reflection","declaration":{"id":1340,"name":"__type","kind":65536,"kindString":"Type literal","flags":{},"children":[{"id":1341,"name":"category_id","kind":1024,"kindString":"Property","flags":{},"sources":[{"fileName":"src/nexus/schemas.ts","line":189,"character":4,"url":"https://github.com/toebeann/npc-vortex-api/blob/b51a728/src/nexus/schemas.ts#L189"}],"type":{"type":"reference","name":"ZodNumber","qualifiedName":"ZodNumber","package":"zod"},"defaultValue":"..."},{"id":1342,"name":"name","kind":1024,"kindString":"Property","flags":{},"sources":[{"fileName":"src/nexus/schemas.ts","line":190,"character":4,"url":"https://github.com/toebeann/npc-vortex-api/blob/b51a728/src/nexus/schemas.ts#L190"}],"type":{"type":"reference","name":"ZodString","qualifiedName":"ZodString","package":"zod"},"defaultValue":"..."},{"id":1343,"name":"parent_category","kind":1024,"kindString":"Property","flags":{},"sources":[{"fileName":"src/nexus/schemas.ts","line":191,"character":4,"url":"https://github.com/toebeann/npc-vortex-api/blob/b51a728/src/nexus/schemas.ts#L191"}],"type":{"type":"reference","typeArguments":[{"type":"tuple","elements":[{"type":"reference","name":"ZodNumber","qualifiedName":"ZodNumber","package":"zod"},{"type":"reference","typeArguments":[{"type":"literal","value":false}],"name":"ZodLiteral","qualifiedName":"ZodLiteral","package":"zod"}]}],"name":"ZodUnion","qualifiedName":"ZodUnion","package":"zod"},"defaultValue":"..."}],"groups":[{"title":"Properties","children":[1341,1342,1343]}],"sources":[{"fileName":"src/nexus/schemas.ts","line":188,"character":40,"url":"https://github.com/toebeann/npc-vortex-api/blob/b51a728/src/nexus/schemas.ts#L188"}]}},{"type":"literal","value":"strip"},{"type":"reference","name":"ZodTypeAny","qualifiedName":"ZodTypeAny","package":"zod"},{"type":"reflection","declaration":{"id":1344,"name":"__type","kind":65536,"kindString":"Type literal","flags":{},"children":[{"id":1346,"name":"category_id","kind":1024,"kindString":"Property","flags":{},"sources":[{"fileName":"src/nexus/schemas.ts","line":189,"character":4,"url":"https://github.com/toebeann/npc-vortex-api/blob/b51a728/src/nexus/schemas.ts#L189"}],"type":{"type":"intrinsic","name":"number"},"defaultValue":"..."},{"id":1345,"name":"name","kind":1024,"kindString":"Property","flags":{},"sources":[{"fileName":"src/nexus/schemas.ts","line":190,"character":4,"url":"https://github.com/toebeann/npc-vortex-api/blob/b51a728/src/nexus/schemas.ts#L190"}],"type":{"type":"intrinsic","name":"string"},"defaultValue":"..."},{"id":1347,"name":"parent_category","kind":1024,"kindString":"Property","flags":{},"sources":[{"fileName":"src/nexus/schemas.ts","line":191,"character":4,"url":"https://github.com/toebeann/npc-vortex-api/blob/b51a728/src/nexus/schemas.ts#L191"}],"type":{"type":"union","types":[{"type":"intrinsic","name":"number"},{"type":"literal","value":false}]},"defaultValue":"..."}],"groups":[{"title":"Properties","children":[1346,1345,1347]}],"sources":[{"fileName":"node_modules/.pnpm/zod@3.21.0/node_modules/zod/lib/types.d.ts","line":977,"character":123}]}},{"type":"reflection","declaration":{"id":1348,"name":"__type","kind":65536,"kindString":"Type literal","flags":{},"children":[{"id":1350,"name":"category_id","kind":1024,"kindString":"Property","flags":{},"sources":[{"fileName":"src/nexus/schemas.ts","line":189,"character":4,"url":"https://github.com/toebeann/npc-vortex-api/blob/b51a728/src/nexus/schemas.ts#L189"}],"type":{"type":"intrinsic","name":"number"},"defaultValue":"..."},{"id":1349,"name":"name","kind":1024,"kindString":"Property","flags":{},"sources":[{"fileName":"src/nexus/schemas.ts","line":190,"character":4,"url":"https://github.com/toebeann/npc-vortex-api/blob/b51a728/src/nexus/schemas.ts#L190"}],"type":{"type":"intrinsic","name":"string"},"defaultValue":"..."},{"id":1351,"name":"parent_category","kind":1024,"kindString":"Property","flags":{},"sources":[{"fileName":"src/nexus/schemas.ts","line":191,"character":4,"url":"https://github.com/toebeann/npc-vortex-api/blob/b51a728/src/nexus/schemas.ts#L191"}],"type":{"type":"union","types":[{"type":"intrinsic","name":"number"},{"type":"literal","value":false}]},"defaultValue":"..."}],"groups":[{"title":"Properties","children":[1350,1349,1351]}],"sources":[{"fileName":"node_modules/.pnpm/zod@3.21.0/node_modules/zod/lib/types.d.ts","line":977,"character":194}]}}],"name":"ZodObject","qualifiedName":"ZodObject","package":"zod"},{"type":"literal","value":"many"}],"name":"ZodArray","qualifiedName":"ZodArray","package":"zod"},"defaultValue":"..."},{"id":1331,"name":"domain_name","kind":1024,"kindString":"Property","flags":{},"sources":[{"fileName":"src/nexus/schemas.ts","line":177,"character":4,"url":"https://github.com/toebeann/npc-vortex-api/blob/b51a728/src/nexus/schemas.ts#L177"}],"type":{"type":"reference","name":"ZodString","qualifiedName":"ZodString","package":"zod"},"defaultValue":"..."},{"id":1337,"name":"downloads","kind":1024,"kindString":"Property","flags":{},"sources":[{"fileName":"src/nexus/schemas.ts","line":184,"character":4,"url":"https://github.com/toebeann/npc-vortex-api/blob/b51a728/src/nexus/schemas.ts#L184"}],"type":{"type":"reference","name":"ZodNumber","qualifiedName":"ZodNumber","package":"zod"},"defaultValue":"..."},{"id":1336,"name":"file_count","kind":1024,"kindString":"Property","flags":{},"sources":[{"fileName":"src/nexus/schemas.ts","line":183,"character":4,"url":"https://github.com/toebeann/npc-vortex-api/blob/b51a728/src/nexus/schemas.ts#L183"}],"type":{"type":"reference","name":"ZodNumber","qualifiedName":"ZodNumber","package":"zod"},"defaultValue":"..."},{"id":1332,"name":"forum_url","kind":1024,"kindString":"Property","flags":{},"sources":[{"fileName":"src/nexus/schemas.ts","line":179,"character":4,"url":"https://github.com/toebeann/npc-vortex-api/blob/b51a728/src/nexus/schemas.ts#L179"}],"type":{"type":"reference","name":"ZodString","qualifiedName":"ZodString","package":"zod"},"defaultValue":"..."},{"id":1334,"name":"genre","kind":1024,"kindString":"Property","flags":{},"sources":[{"fileName":"src/nexus/schemas.ts","line":181,"character":4,"url":"https://github.com/toebeann/npc-vortex-api/blob/b51a728/src/nexus/schemas.ts#L181"}],"type":{"type":"reference","name":"ZodString","qualifiedName":"ZodString","package":"zod"},"defaultValue":"..."},{"id":1329,"name":"id","kind":1024,"kindString":"Property","flags":{},"sources":[{"fileName":"src/nexus/schemas.ts","line":176,"character":4,"url":"https://github.com/toebeann/npc-vortex-api/blob/b51a728/src/nexus/schemas.ts#L176"}],"type":{"type":"reference","name":"ZodNumber","qualifiedName":"ZodNumber","package":"zod"},"defaultValue":"..."},{"id":1335,"name":"mods","kind":1024,"kindString":"Property","flags":{},"sources":[{"fileName":"src/nexus/schemas.ts","line":182,"character":4,"url":"https://github.com/toebeann/npc-vortex-api/blob/b51a728/src/nexus/schemas.ts#L182"}],"type":{"type":"reference","name":"ZodNumber","qualifiedName":"ZodNumber","package":"zod"},"defaultValue":"..."},{"id":1330,"name":"name","kind":1024,"kindString":"Property","flags":{},"sources":[{"fileName":"src/nexus/schemas.ts","line":178,"character":4,"url":"https://github.com/toebeann/npc-vortex-api/blob/b51a728/src/nexus/schemas.ts#L178"}],"type":{"type":"reference","name":"ZodString","qualifiedName":"ZodString","package":"zod"},"defaultValue":"..."},{"id":1333,"name":"nexusmods_url","kind":1024,"kindString":"Property","flags":{},"sources":[{"fileName":"src/nexus/schemas.ts","line":180,"character":4,"url":"https://github.com/toebeann/npc-vortex-api/blob/b51a728/src/nexus/schemas.ts#L180"}],"type":{"type":"reference","name":"ZodString","qualifiedName":"ZodString","package":"zod"},"defaultValue":"..."}],"groups":[{"title":"Properties","children":[1338,1339,1331,1337,1336,1332,1334,1329,1335,1330,1333]}],"sources":[{"fileName":"node_modules/.pnpm/zod@3.21.0/node_modules/zod/lib/helpers/util.d.ts","line":15,"character":38}]}},{"type":"literal","value":"strip"},{"type":"reference","name":"ZodTypeAny","qualifiedName":"ZodTypeAny","package":"zod"},{"type":"reflection","declaration":{"id":1352,"name":"__type","kind":65536,"kindString":"Type literal","flags":{},"children":[{"id":1362,"name":"approved_date","kind":1024,"kindString":"Property","flags":{},"sources":[{"fileName":"src/nexus/schemas.ts","line":185,"character":4,"url":"https://github.com/toebeann/npc-vortex-api/blob/b51a728/src/nexus/schemas.ts#L185"}],"type":{"type":"intrinsic","name":"number"},"defaultValue":"..."},{"id":1363,"name":"categories","kind":1024,"kindString":"Property","flags":{},"sources":[{"fileName":"src/nexus/schemas.ts","line":195,"character":4,"url":"https://github.com/toebeann/npc-vortex-api/blob/b51a728/src/nexus/schemas.ts#L195"}],"type":{"type":"array","elementType":{"type":"reflection","declaration":{"id":1364,"name":"__type","kind":65536,"kindString":"Type literal","flags":{},"children":[{"id":1366,"name":"category_id","kind":1024,"kindString":"Property","flags":{},"sources":[{"fileName":"src/nexus/schemas.ts","line":189,"character":4,"url":"https://github.com/toebeann/npc-vortex-api/blob/b51a728/src/nexus/schemas.ts#L189"}],"type":{"type":"intrinsic","name":"number"},"defaultValue":"..."},{"id":1365,"name":"name","kind":1024,"kindString":"Property","flags":{},"sources":[{"fileName":"src/nexus/schemas.ts","line":190,"character":4,"url":"https://github.com/toebeann/npc-vortex-api/blob/b51a728/src/nexus/schemas.ts#L190"}],"type":{"type":"intrinsic","name":"string"},"defaultValue":"..."},{"id":1367,"name":"parent_category","kind":1024,"kindString":"Property","flags":{},"sources":[{"fileName":"src/nexus/schemas.ts","line":191,"character":4,"url":"https://github.com/toebeann/npc-vortex-api/blob/b51a728/src/nexus/schemas.ts#L191"}],"type":{"type":"union","types":[{"type":"intrinsic","name":"number"},{"type":"literal","value":false}]},"defaultValue":"..."}],"groups":[{"title":"Properties","children":[1366,1365,1367]}],"sources":[{"fileName":"node_modules/.pnpm/zod@3.21.0/node_modules/zod/lib/types.d.ts","line":977,"character":123}]}}},"defaultValue":"..."},{"id":1355,"name":"domain_name","kind":1024,"kindString":"Property","flags":{},"sources":[{"fileName":"src/nexus/schemas.ts","line":177,"character":4,"url":"https://github.com/toebeann/npc-vortex-api/blob/b51a728/src/nexus/schemas.ts#L177"}],"type":{"type":"intrinsic","name":"string"},"defaultValue":"..."},{"id":1361,"name":"downloads","kind":1024,"kindString":"Property","flags":{},"sources":[{"fileName":"src/nexus/schemas.ts","line":184,"character":4,"url":"https://github.com/toebeann/npc-vortex-api/blob/b51a728/src/nexus/schemas.ts#L184"}],"type":{"type":"intrinsic","name":"number"},"defaultValue":"..."},{"id":1360,"name":"file_count","kind":1024,"kindString":"Property","flags":{},"sources":[{"fileName":"src/nexus/schemas.ts","line":183,"character":4,"url":"https://github.com/toebeann/npc-vortex-api/blob/b51a728/src/nexus/schemas.ts#L183"}],"type":{"type":"intrinsic","name":"number"},"defaultValue":"..."},{"id":1356,"name":"forum_url","kind":1024,"kindString":"Property","flags":{},"sources":[{"fileName":"src/nexus/schemas.ts","line":179,"character":4,"url":"https://github.com/toebeann/npc-vortex-api/blob/b51a728/src/nexus/schemas.ts#L179"}],"type":{"type":"intrinsic","name":"string"},"defaultValue":"..."},{"id":1358,"name":"genre","kind":1024,"kindString":"Property","flags":{},"sources":[{"fileName":"src/nexus/schemas.ts","line":181,"character":4,"url":"https://github.com/toebeann/npc-vortex-api/blob/b51a728/src/nexus/schemas.ts#L181"}],"type":{"type":"intrinsic","name":"string"},"defaultValue":"..."},{"id":1353,"name":"id","kind":1024,"kindString":"Property","flags":{},"sources":[{"fileName":"src/nexus/schemas.ts","line":176,"character":4,"url":"https://github.com/toebeann/npc-vortex-api/blob/b51a728/src/nexus/schemas.ts#L176"}],"type":{"type":"intrinsic","name":"number"},"defaultValue":"..."},{"id":1359,"name":"mods","kind":1024,"kindString":"Property","flags":{},"sources":[{"fileName":"src/nexus/schemas.ts","line":182,"character":4,"url":"https://github.com/toebeann/npc-vortex-api/blob/b51a728/src/nexus/schemas.ts#L182"}],"type":{"type":"intrinsic","name":"number"},"defaultValue":"..."},{"id":1354,"name":"name","kind":1024,"kindString":"Property","flags":{},"sources":[{"fileName":"src/nexus/schemas.ts","line":178,"character":4,"url":"https://github.com/toebeann/npc-vortex-api/blob/b51a728/src/nexus/schemas.ts#L178"}],"type":{"type":"intrinsic","name":"string"},"defaultValue":"..."},{"id":1357,"name":"nexusmods_url","kind":1024,"kindString":"Property","flags":{},"sources":[{"fileName":"src/nexus/schemas.ts","line":180,"character":4,"url":"https://github.com/toebeann/npc-vortex-api/blob/b51a728/src/nexus/schemas.ts#L180"}],"type":{"type":"intrinsic","name":"string"},"defaultValue":"..."}],"groups":[{"title":"Properties","children":[1362,1363,1355,1361,1360,1356,1358,1353,1359,1354,1357]}],"sources":[{"fileName":"node_modules/.pnpm/zod@3.21.0/node_modules/zod/lib/types.d.ts","line":453,"character":53}]}},{"type":"reflection","declaration":{"id":1368,"name":"__type","kind":65536,"kindString":"Type literal","flags":{},"children":[{"id":1378,"name":"approved_date","kind":1024,"kindString":"Property","flags":{},"sources":[{"fileName":"src/nexus/schemas.ts","line":185,"character":4,"url":"https://github.com/toebeann/npc-vortex-api/blob/b51a728/src/nexus/schemas.ts#L185"}],"type":{"type":"intrinsic","name":"number"},"defaultValue":"..."},{"id":1379,"name":"categories","kind":1024,"kindString":"Property","flags":{},"sources":[{"fileName":"src/nexus/schemas.ts","line":195,"character":4,"url":"https://github.com/toebeann/npc-vortex-api/blob/b51a728/src/nexus/schemas.ts#L195"}],"type":{"type":"array","elementType":{"type":"reflection","declaration":{"id":1380,"name":"__type","kind":65536,"kindString":"Type literal","flags":{},"children":[{"id":1382,"name":"category_id","kind":1024,"kindString":"Property","flags":{},"sources":[{"fileName":"src/nexus/schemas.ts","line":189,"character":4,"url":"https://github.com/toebeann/npc-vortex-api/blob/b51a728/src/nexus/schemas.ts#L189"}],"type":{"type":"intrinsic","name":"number"},"defaultValue":"..."},{"id":1381,"name":"name","kind":1024,"kindString":"Property","flags":{},"sources":[{"fileName":"src/nexus/schemas.ts","line":190,"character":4,"url":"https://github.com/toebeann/npc-vortex-api/blob/b51a728/src/nexus/schemas.ts#L190"}],"type":{"type":"intrinsic","name":"string"},"defaultValue":"..."},{"id":1383,"name":"parent_category","kind":1024,"kindString":"Property","flags":{},"sources":[{"fileName":"src/nexus/schemas.ts","line":191,"character":4,"url":"https://github.com/toebeann/npc-vortex-api/blob/b51a728/src/nexus/schemas.ts#L191"}],"type":{"type":"union","types":[{"type":"intrinsic","name":"number"},{"type":"literal","value":false}]},"defaultValue":"..."}],"groups":[{"title":"Properties","children":[1382,1381,1383]}],"sources":[{"fileName":"node_modules/.pnpm/zod@3.21.0/node_modules/zod/lib/types.d.ts","line":977,"character":194}]}}},"defaultValue":"..."},{"id":1371,"name":"domain_name","kind":1024,"kindString":"Property","flags":{},"sources":[{"fileName":"src/nexus/schemas.ts","line":177,"character":4,"url":"https://github.com/toebeann/npc-vortex-api/blob/b51a728/src/nexus/schemas.ts#L177"}],"type":{"type":"intrinsic","name":"string"},"defaultValue":"..."},{"id":1377,"name":"downloads","kind":1024,"kindString":"Property","flags":{},"sources":[{"fileName":"src/nexus/schemas.ts","line":184,"character":4,"url":"https://github.com/toebeann/npc-vortex-api/blob/b51a728/src/nexus/schemas.ts#L184"}],"type":{"type":"intrinsic","name":"number"},"defaultValue":"..."},{"id":1376,"name":"file_count","kind":1024,"kindString":"Property","flags":{},"sources":[{"fileName":"src/nexus/schemas.ts","line":183,"character":4,"url":"https://github.com/toebeann/npc-vortex-api/blob/b51a728/src/nexus/schemas.ts#L183"}],"type":{"type":"intrinsic","name":"number"},"defaultValue":"..."},{"id":1372,"name":"forum_url","kind":1024,"kindString":"Property","flags":{},"sources":[{"fileName":"src/nexus/schemas.ts","line":179,"character":4,"url":"https://github.com/toebeann/npc-vortex-api/blob/b51a728/src/nexus/schemas.ts#L179"}],"type":{"type":"intrinsic","name":"string"},"defaultValue":"..."},{"id":1374,"name":"genre","kind":1024,"kindString":"Property","flags":{},"sources":[{"fileName":"src/nexus/schemas.ts","line":181,"character":4,"url":"https://github.com/toebeann/npc-vortex-api/blob/b51a728/src/nexus/schemas.ts#L181"}],"type":{"type":"intrinsic","name":"string"},"defaultValue":"..."},{"id":1369,"name":"id","kind":1024,"kindString":"Property","flags":{},"sources":[{"fileName":"src/nexus/schemas.ts","line":176,"character":4,"url":"https://github.com/toebeann/npc-vortex-api/blob/b51a728/src/nexus/schemas.ts#L176"}],"type":{"type":"intrinsic","name":"number"},"defaultValue":"..."},{"id":1375,"name":"mods","kind":1024,"kindString":"Property","flags":{},"sources":[{"fileName":"src/nexus/schemas.ts","line":182,"character":4,"url":"https://github.com/toebeann/npc-vortex-api/blob/b51a728/src/nexus/schemas.ts#L182"}],"type":{"type":"intrinsic","name":"number"},"defaultValue":"..."},{"id":1370,"name":"name","kind":1024,"kindString":"Property","flags":{},"sources":[{"fileName":"src/nexus/schemas.ts","line":178,"character":4,"url":"https://github.com/toebeann/npc-vortex-api/blob/b51a728/src/nexus/schemas.ts#L178"}],"type":{"type":"intrinsic","name":"string"},"defaultValue":"..."},{"id":1373,"name":"nexusmods_url","kind":1024,"kindString":"Property","flags":{},"sources":[{"fileName":"src/nexus/schemas.ts","line":180,"character":4,"url":"https://github.com/toebeann/npc-vortex-api/blob/b51a728/src/nexus/schemas.ts#L180"}],"type":{"type":"intrinsic","name":"string"},"defaultValue":"..."}],"groups":[{"title":"Properties","children":[1378,1379,1371,1377,1376,1372,1374,1369,1375,1370,1373]}],"sources":[{"fileName":"node_modules/.pnpm/zod@3.21.0/node_modules/zod/lib/types.d.ts","line":453,"character":53}]}}],"name":"ZodObject","qualifiedName":"ZodObject","package":"zod"},"defaultValue":"...","is":{"declaration":true},"location":{"query":"nexus.schemas.Variable.iGameInfoSchema","hash":""},"text":{},"parentId":555}
