{"id":3705,"name":"ruleTypeSchema","kind":32,"kindString":"Variable","flags":{"isConst":true},"children":[],"sources":[{"fileName":"src/vortex/schemas.ts","fullFileName":"/home/runner/work/npc-vortex-api/npc-vortex-api/src/vortex/schemas.ts","line":74,"character":13,"url":"https://github.com/toebeann/npc-vortex-api/blob/2b3d665/src/vortex/schemas.ts#L74"}],"type":{"type":"reference","typeArguments":[{"type":"tuple","elements":[{"type":"reference","typeArguments":[{"type":"literal","value":"before"}],"name":"ZodLiteral","qualifiedName":"ZodLiteral","package":"zod"},{"type":"reference","typeArguments":[{"type":"literal","value":"after"}],"name":"ZodLiteral","qualifiedName":"ZodLiteral","package":"zod"},{"type":"reference","typeArguments":[{"type":"literal","value":"requires"}],"name":"ZodLiteral","qualifiedName":"ZodLiteral","package":"zod"},{"type":"reference","typeArguments":[{"type":"literal","value":"conflicts"}],"name":"ZodLiteral","qualifiedName":"ZodLiteral","package":"zod"},{"type":"reference","typeArguments":[{"type":"literal","value":"recommends"}],"name":"ZodLiteral","qualifiedName":"ZodLiteral","package":"zod"},{"type":"reference","typeArguments":[{"type":"literal","value":"provides"}],"name":"ZodLiteral","qualifiedName":"ZodLiteral","package":"zod"}]}],"name":"ZodUnion","qualifiedName":"ZodUnion","package":"zod"},"defaultValue":"...","is":{"declaration":true},"location":{"query":"vortex.schemas.Variable.ruleTypeSchema","hash":""},"text":{},"parentId":3509}
